rtl/alu.v
module alu(
    input [31:0]a, 
    input [31:0]b, 
    input [3:0]alu_ctrl, 
    output reg [31:0]out, 
    output reg zero, 
    output reg carry, 
    output reg overflow, 
    output reg negative
    );
    
    reg [32:0]temp;

    always @(*) begin
        // default
        out = 32'b0;
        zero = 1'b0;
        carry = 1'b0;
        overflow = 1'b0;
        negative = 1'b0;
        temp = 33'b0;

        case(alu_ctrl)
            4'h0: begin                                             // add
                temp = {1'b0, a} + {1'b0, b};
                out = temp[31:0];
                carry = temp[32];

                // signed overflow for addition
                overflow = (a[31] == b[31]) && (out[31] != a[31]);
            end
            4'h1: begin   
                temp = {1'b0, a} - {1'b0, b};                       // sub
                out = temp[31:0];

                // carry = 1 when no borrow
                carry = (a >= b);

                // signed overflow for subtraction
                overflow = (a[31] != b[31]) && (out[31] != a[31]);
            end
            4'h2: out = a & b;                                      // and
            4'h3: out = a | b;                                      // or
            4'h4: out = a ^ b;                                      // xor
            4'h5: out = a << b[4:0];                                // sll
            4'h6: out = a >> b[4:0];                                // srl
            4'h7: out = $signed(a) >>> b[4:0];                      // sra
            4'h8: out = ($signed(a) < $signed(b)) ? 32'h1 : 32'h0;  // slt
            4'h9: out = (a < b) ? 32'h1 : 32'h0;                    // sltu
            default: out = 32'b0;
        endcase

        // set zero & negative
        zero = (out == 32'b0);
        negative = out[31];
    end
endmodule

tb/tb_alu.v
`timescale 1ns / 1ps  // Unit: 1 nanosecond, Precision: 1 picosecond

module tb_alu;
    reg  [31:0] a;
    reg  [31:0] b;
    reg  [3:0]  alu_ctrl;
    wire [31:0] out;
    wire        zero;
    wire        carry;
    wire        overflow;
    wire        negative;

    localparam ADD  = 4'h0;
    localparam SUB  = 4'h1;
    localparam AND  = 4'h2;
    localparam OR   = 4'h3;
    localparam XOR  = 4'h4;
    localparam SLL  = 4'h5;
    localparam SRL  = 4'h6;
    localparam SRA  = 4'h7;
    localparam SLT  = 4'h8;
    localparam SLTU = 4'h9;

    integer errors;

    alu dut (
        .a(a),
        .b(b),
        .alu_ctrl(alu_ctrl),
        .out(out),
        .zero(zero),
        .carry(carry),
        .overflow(overflow),
        .negative(negative)
    );

    // PASS/FAIL message
    task check;
        input [127:0]   test_name;
        input [31:0]    expected;
        input           expected_zero;
        input           expected_carry;
        input           expected_overflow;
        input           expected_negative;
        begin 
            #1;
            if ((out !== expected) ||
                (zero !== expected_zero) ||
                (carry !== expected_carry) ||
                (overflow !== expected_overflow) ||
                (negative !== expected_negative)) begin
                errors = errors + 1;
                $display("FAIL: test=%s a=%h b=%h alu_ctrl=%b expected out=%h zero=%b carry=%b overflow=%b negative=%b got out=%h zero=%b carry=%b overflow=%b negative=%b",
                test_name, a, b, alu_ctrl, expected, expected_zero, expected_carry, expected_overflow, expected_negative,
                out, zero, carry, overflow, negative);
            end else begin
                $display("PASS: test=%s a=%h b=%h alu_ctrl=%b out=%h zero=%b carry=%b overflow=%b negative=%b",
                test_name, a, b, alu_ctrl, out, zero, carry, overflow, negative);
            end
        end
    endtask

    initial begin
        $dumpfile("waves/alu.vcd");
        $dumpvars(0, tb_alu);

        errors = 0;

        // ADD: 5 + 3 = 8
        a = 32'd5;
        b = 32'd3;
        alu_ctrl = ADD;
        check("ADD ", 32'd8, 1'b0, 1'b0, 1'b0, 1'b0);

        // ADD: carry out
        a = 32'hffff_ffff;
        b = 32'd1;
        alu_ctrl = ADD;
        check("ADD + carry out", 32'd0, 1'b1, 1'b1, 1'b0, 1'b0);

        // ADD: signed overflow
        a = 32'h7fff_ffff;
        b = 32'd1;
        alu_ctrl = ADD;
        check("ADD + overflow", 32'h8000_0000, 1'b0, 1'b0, 1'b1, 1'b1);

        // SUB: 5 - 3 = 2
        a = 32'd5;
        b = 32'd3;
        alu_ctrl = SUB;
        check("SUB ", 32'd2, 1'b0, 1'b1, 1'b0, 1'b0);

        // SUB: borrow and negative result
        a = 32'd3;
        b = 32'd5;
        alu_ctrl = SUB;
        check("SUB + borrow/neg", 32'hffff_fffe, 1'b0, 1'b0, 1'b0, 1'b1);

        // SUB: signed overflow
        a = 32'h8000_0000;
        b = 32'd1;
        alu_ctrl = SUB;
        check("SUB + overflow", 32'h7fff_ffff, 1'b0, 1'b1, 1'b1, 1'b0);

        // AND
        a = 32'ha5a5_5a5a;
        b = 32'hff00_0ff0;
        alu_ctrl = AND;
        check("AND ", 32'ha500_0a50, 1'b0, 1'b0, 1'b0, 1'b1);

        // OR
        a = 32'ha5a5_5a5a;
        b = 32'hff00_0ff0;
        alu_ctrl = OR;
        check("OR  ", 32'hffa5_5ffa, 1'b0, 1'b0, 1'b0, 1'b1);

        // XOR
        a = 32'ha5a5_5a5a;
        b = 32'hff00_0ff0;
        alu_ctrl = XOR;
        check("XOR ", 32'h5aa5_55aa, 1'b0, 1'b0, 1'b0, 1'b0);

        // SLL
        a = 32'h0000_0001;
        b = 32'd4;
        alu_ctrl = SLL;
        check("SLL ", 32'h0000_0010, 1'b0, 1'b0, 1'b0, 1'b0);

        // SRL
        a = 32'h8000_0000;
        b = 32'd4;
        alu_ctrl = SRL;
        check("SRL ", 32'h0800_0000, 1'b0, 1'b0, 1'b0, 1'b0);

        // SRA
        a = 32'h8000_0000;
        b = 32'd4;
        alu_ctrl = SRA;
        check("SRA ", 32'hf800_0000, 1'b0, 1'b0, 1'b0, 1'b1);

        // SLT: signed
        a = 32'hffff_ffff;
        b = 32'd1;
        alu_ctrl = SLT;
        check("SLT ", 32'd1, 1'b0, 1'b0, 1'b0, 1'b0);

        // SLTU: unsigned
        a = 32'hffff_ffff;
        b = 32'd1;
        alu_ctrl = SLTU;
        check("SLTU", 32'd0, 1'b1, 1'b0, 1'b0, 1'b0);

        // Default case
        a = 32'h1234_5678;
        b = 32'h8765_4321;
        alu_ctrl = 4'ha;
        check("DEFAULT", 32'd0, 1'b1, 1'b0, 1'b0, 1'b0);

        if (errors == 0) begin
            $display("All ALU tests passed.");
        end else begin
            $display("ALU tests failed with %0d error(s).", errors);
        end

        $finish;

    end

endmodule

waves/alu.vcd
$date
	Thu Jun 25 15:29:34 2026
$end
$version
	Icarus Verilog
$end
$timescale
	1ps
$end
$scope module tb_alu $end
$var wire 1 ! zero $end
$var wire 1 " overflow $end
$var wire 32 # out [31:0] $end
$var wire 1 $ negative $end
$var wire 1 % carry $end
$var parameter 4 & ADD $end
$var parameter 4 ' AND $end
$var parameter 4 ( OR $end
$var parameter 4 ) SLL $end
$var parameter 4 * SLT $end
$var parameter 4 + SLTU $end
$var parameter 4 , SRA $end
$var parameter 4 - SRL $end
$var parameter 4 . SUB $end
$var parameter 4 / XOR $end
$var reg 32 0 a [31:0] $end
$var reg 4 1 alu_ctrl [3:0] $end
$var reg 32 2 b [31:0] $end
$var integer 32 3 errors [31:0] $end
$scope module dut $end
$var wire 32 4 a [31:0] $end
$var wire 4 5 alu_ctrl [3:0] $end
$var wire 32 6 b [31:0] $end
$var reg 1 % carry $end
$var reg 1 $ negative $end
$var reg 32 7 out [31:0] $end
$var reg 1 " overflow $end
$var reg 33 8 temp [32:0] $end
$var reg 1 ! zero $end
$upscope $end
$scope task check $end
$var reg 32 9 expected [31:0] $end
$var reg 1 : expected_carry $end
$var reg 1 ; expected_negative $end
$var reg 1 < expected_overflow $end
$var reg 1 = expected_zero $end
$var reg 128 > test_name [127:0] $end
$upscope $end
$upscope $end
$enddefinitions $end
$comment Show the parameter values. $end
$dumpall
b100 /
b1 .
b110 -
b111 ,
b1001 +
b1000 *
b101 )
b11 (
b10 '
b0 &
$end
#0
$dumpvars
b1000001010001000100010000100000 >
0=
0<
0;
0:
b1000 9
b1000 8
b1000 7
b11 6
b0 5
b101 4
b0 3
b11 2
b0 1
b101 0
0%
0$
b1000 #
0"
0!
$end
#1000
1!
1%
b100000000000000000000000000000000 8
b0 #
b0 7
1:
1=
b0 9
b10000010100010001000100001000000010101100100000011000110110000101110010011100100111100100100000011011110111010101110100 >
b1 2
b1 6
b11111111111111111111111111111111 0
b11111111111111111111111111111111 4
#2000
1$
1"
b10000000000000000000000000000000 #
b10000000000000000000000000000000 7
b10000000000000000000000000000000 8
0%
0!
1;
1<
0:
0=
b10000000000000000000000000000000 9
b100000101000100010001000010000000101011001000000110111101110110011001010111001001100110011011000110111101110111 >
b1111111111111111111111111111111 0
b1111111111111111111111111111111 4
#3000
1%
b10 8
0$
0"
b10 #
b10 7
0;
0<
1:
b10 9
b1010011010101010100001000100000 >
b1 1
b1 5
b11 2
b11 6
b101 0
b101 4
#4000
1$
b111111111111111111111111111111110 8
0%
b11111111111111111111111111111110 #
b11111111111111111111111111111110 7
1;
0:
b11111111111111111111111111111110 9
b1010011010101010100001000100000001010110010000001100010011011110111001001110010011011110111011100101111011011100110010101100111 >
b101 2
b101 6
b11 0
b11 4
#5000
1"
1%
b1111111111111111111111111111111 8
0$
b1111111111111111111111111111111 #
b1111111111111111111111111111111 7
0;
1<
1:
b1111111111111111111111111111111 9
b101001101010101010000100010000000101011001000000110111101110110011001010111001001100110011011000110111101110111 >
b1 2
b1 6
b10000000000000000000000000000000 0
b10000000000000000000000000000000 4
#6000
1$
b0 8
0"
0%
b10100101000000000000101001010000 #
b10100101000000000000101001010000 7
1;
0<
0:
b10100101000000000000101001010000 9
b1000001010011100100010000100000 >
b10 1
b10 5
b11111111000000000000111111110000 2
b11111111000000000000111111110000 6
b10100101101001010101101001011010 0
b10100101101001010101101001011010 4
#7000
1$
b11111111101001010101111111111010 #
b11111111101001010101111111111010 7
b11111111101001010101111111111010 9
b1001111010100100010000000100000 >
b11 1
b11 5
#8000
0$
b1011010101001010101010110101010 #
b1011010101001010101010110101010 7
0;
b1011010101001010101010110101010 9
b1011000010011110101001000100000 >
b100 1
b100 5
#9000
b10000 #
b10000 7
b10000 9
b1010011010011000100110000100000 >
b101 1
b101 5
b100 2
b100 6
b1 0
b1 4
#10000
b1000000000000000000000000000 #
b1000000000000000000000000000 7
b1000000000000000000000000000 9
b1010011010100100100110000100000 >
b110 1
b110 5
b10000000000000000000000000000000 0
b10000000000000000000000000000000 4
#11000
1$
b11111000000000000000000000000000 #
b11111000000000000000000000000000 7
1;
b11111000000000000000000000000000 9
b1010011010100100100000100100000 >
b111 1
b111 5
#12000
0$
b1 #
b1 7
0;
b1 9
b1010011010011000101010000100000 >
b1000 1
b1000 5
b1 2
b1 6
b11111111111111111111111111111111 0
b11111111111111111111111111111111 4
#13000
1!
b0 #
b0 7
1=
b0 9
b1010011010011000101010001010101 >
b1001 1
b1001 5
#14000
1!
b1000100010001010100011001000001010101010100110001010100 >
b1010 1
b1010 5
b10000111011001010100001100100001 2
b10000111011001010100001100100001 6
b10010001101000101011001111000 0
b10010001101000101011001111000 4
