rtl/control.v
module control (
    input [6:0] opcode,
    input [2:0] func3,
    input [6:0] func7,
    output reg reg_write,
    output reg mem_read,
    output reg mem_write,
    output reg alu_src,         // 0 = rv2, 1 = imm
    output reg branch,
    output reg jump,
    output reg [3:0] alu_ctrl,  // 0 = add, 1 = sub, ... 
    output reg [1:0] result_src // 00 = ALU result, 01 = mem read data, 10 = PC + 4, 11 = imm
);
    // opcode
    localparam LUI      = 7'b0110111; // lui
    localparam OP       = 7'b0110011; // add, sub, ...
    localparam OP_IMM   = 7'b0010011; // addi, slti, xori, ... 
    localparam LOAD     = 7'b0000011; // lb, lbu, lh, lhu, lw
    localparam STORE    = 7'b0100011; // sb, sh, sw
    localparam BRANCH   = 7'b1100011; // beq, bne, blt, bge, bltu, bgeu
    localparam JAL      = 7'b1101111; // jal
    localparam JALR     = 7'b1100111; // jalr

    // func3
    localparam ADD3     = 3'b000;
    localparam SUB3     = ADD3;
    localparam SLL3     = 3'b001;
    localparam SLT3     = 3'b010;
    localparam SLTU3    = 3'b011;
    localparam XOR3     = 3'b100;
    localparam SRL3     = 3'b101;
    localparam SRA3     = SRL3;
    localparam OR3      = 3'b110;
    localparam AND3     = 3'b111;

    localparam BEQ3     = ADD3;
    localparam BNE3     = SLL3;
    localparam BLT3     = XOR3;
    localparam BGE3     = SRL3;
    localparam BLTU3    = OR3;
    localparam BGEU3    = AND3;

    // func7
    localparam ADD7     = 7'b0000000;
    localparam SLL7     = ADD7;
    localparam SLT7     = ADD7;
    localparam SLTU7    = ADD7;
    localparam XOR7     = ADD7;
    localparam SRL7     = ADD7;
    localparam OR7      = ADD7;
    localparam AND7     = ADD7;
    localparam SUB7     = 7'b0100000;
    localparam SRA7     = SUB7;

    // alu_ctrl
    localparam ALU_ADD  = 4'h0;
    localparam ALU_SUB  = 4'h1;
    localparam ALU_AND  = 4'h2;
    localparam ALU_OR   = 4'h3;
    localparam ALU_XOR  = 4'h4;
    localparam ALU_SLL  = 4'h5;
    localparam ALU_SRL  = 4'h6;
    localparam ALU_SRA  = 4'h7;
    localparam ALU_SLT  = 4'h8;
    localparam ALU_SLTU = 4'h9;

    // result_src
    localparam RESULT_ALU = 2'b00;
    localparam RESULT_MEM = 2'b01;
    localparam RESULT_PC4 = 2'b10;
    localparam RESULT_IMM = 2'b11;

    always @(*) begin
        reg_write   = 1'b0;
        mem_read    = 1'b0;
        mem_write   = 1'b0;
        alu_src     = 1'b0;
        branch      = 1'b0;
        jump        = 1'b0;
        alu_ctrl    = ALU_ADD;
        result_src  = RESULT_ALU;

        case(opcode)
            LUI: begin
                reg_write   = 1'b1;
                result_src  = RESULT_IMM;
            end
            OP: begin
                reg_write   = 1'b1;
                alu_src     = 1'b0;

                case({func7, func3})
                    {ADD7, ADD3}:   alu_ctrl = ALU_ADD;
                    {SUB7, SUB3}:   alu_ctrl = ALU_SUB;
                    {SLL7, SLL3}:   alu_ctrl = ALU_SLL;
                    {SLT7, SLT3}:   alu_ctrl = ALU_SLT;
                    {SLTU7, SLTU3}: alu_ctrl = ALU_SLTU;
                    {XOR7, XOR3}:   alu_ctrl = ALU_XOR;
                    {SRL7, SRL3}:   alu_ctrl = ALU_SRL;
                    {SRA7, SRA3}:   alu_ctrl = ALU_SRA;
                    {OR7, OR3}:     alu_ctrl = ALU_OR;
                    {AND7, AND3}:   alu_ctrl = ALU_AND;
                    default:        alu_ctrl = ALU_ADD;
                endcase
            end
            OP_IMM: begin
                reg_write   = 1'b1;
                alu_src     = 1'b1;

                case(func3)
                    ADD3:    alu_ctrl = ALU_ADD;
                    SLL3:    alu_ctrl = ALU_SLL;
                    SLT3:    alu_ctrl = ALU_SLT;
                    SLTU3:   alu_ctrl = ALU_SLTU;
                    XOR3:    alu_ctrl = ALU_XOR;
                    SRL3:    alu_ctrl = (func7 == SRA7) ? ALU_SRA : ALU_SRL;
                    OR3:     alu_ctrl = ALU_OR;
                    AND3:    alu_ctrl = ALU_AND;
                    default: alu_ctrl = ALU_ADD;
                endcase
            end
            LOAD: begin
                reg_write   = 1'b1;
                mem_read    = 1'b1;
                alu_src     = 1'b1;
                alu_ctrl    = ALU_ADD;
                result_src  = RESULT_MEM;
            end
            STORE: begin
                mem_write   = 1'b1;
                alu_src     = 1'b1;
                alu_ctrl    = ALU_ADD;
            end
            BRANCH: begin
                branch      = 1'b1;

                case(func3)
                    BEQ3, BNE3:   alu_ctrl = ALU_SUB;
                    BLT3, BGE3:   alu_ctrl = ALU_SLT;
                    BLTU3, BGEU3: alu_ctrl = ALU_SLTU;
                    default:      alu_ctrl = ALU_SUB;
                endcase
            end
            JAL: begin
                reg_write   = 1'b1;
                jump        = 1'b1;
                result_src  = RESULT_PC4;
            end
            JALR: begin
                reg_write   = 1'b1;
                alu_src     = 1'b1;
                jump        = 1'b1;
                alu_ctrl    = ALU_ADD;
                result_src  = RESULT_PC4;
            end
            default: begin
            end
        endcase
    end

endmodule

tb/tb_control.v
`timescale 1ns / 1ps

module tb_control;
    reg [6:0] opcode;
    reg [2:0] func3;
    reg [6:0] func7;

    wire reg_write;
    wire mem_read;
    wire mem_write;
    wire alu_src;
    wire branch;
    wire jump;
    wire [3:0] alu_ctrl;
    wire [1:0] result_src;

    localparam LUI      = 7'b0110111;
    localparam OP       = 7'b0110011;
    localparam OP_IMM   = 7'b0010011;
    localparam LOAD     = 7'b0000011;
    localparam STORE    = 7'b0100011;
    localparam BRANCH   = 7'b1100011;
    localparam JAL      = 7'b1101111;
    localparam JALR     = 7'b1100111;

    localparam ADD3     = 3'b000;
    localparam SUB3     = ADD3;
    localparam SLL3     = 3'b001;
    localparam SLT3     = 3'b010;
    localparam SLTU3    = 3'b011;
    localparam XOR3     = 3'b100;
    localparam SRL3     = 3'b101;
    localparam SRA3     = SRL3;
    localparam OR3      = 3'b110;
    localparam AND3     = 3'b111;

    localparam ADD7     = 7'b0000000;
    localparam SUB7     = 7'b0100000;
    localparam SRA7     = SUB7;

    localparam ALU_ADD  = 4'h0;
    localparam ALU_SUB  = 4'h1;
    localparam ALU_AND  = 4'h2;
    localparam ALU_OR   = 4'h3;
    localparam ALU_XOR  = 4'h4;
    localparam ALU_SLL  = 4'h5;
    localparam ALU_SRL  = 4'h6;
    localparam ALU_SRA  = 4'h7;
    localparam ALU_SLT  = 4'h8;
    localparam ALU_SLTU = 4'h9;

    localparam RESULT_ALU = 2'b00;
    localparam RESULT_MEM = 2'b01;
    localparam RESULT_PC4 = 2'b10;
    localparam RESULT_IMM = 2'b11;

    integer errors;

    control dut(
        .opcode(opcode),
        .func3(func3),
        .func7(func7),
        .reg_write(reg_write),
        .mem_read(mem_read),
        .mem_write(mem_write),
        .alu_src(alu_src),
        .branch(branch),
        .jump(jump),
        .alu_ctrl(alu_ctrl),
        .result_src(result_src)
    );

    task check;
        input [255:0] test_name;
        input exp_reg_write;
        input exp_mem_read;
        input exp_mem_write;
        input exp_alu_src;
        input exp_branch;
        input exp_jump;
        input [3:0] exp_alu_ctrl;
        input [1:0] exp_result_src;
        begin
            #1;
            if ((reg_write !== exp_reg_write) ||
                (mem_read !== exp_mem_read) ||
                (mem_write !== exp_mem_write) ||
                (alu_src !== exp_alu_src) ||
                (branch !== exp_branch) ||
                (jump !== exp_jump) ||
                (alu_ctrl !== exp_alu_ctrl) ||
                (result_src !== exp_result_src)) begin
                $display("FAIL: test=%s opcode=%b func3=%b func7=%b exp reg_write=%b mem_read=%b mem_write=%b alu_src=%b branch=%b jump=%b alu_ctrl=%h result_src=%b got reg_write=%b mem_read=%b mem_write=%b alu_src=%b branch=%b jump=%b alu_ctrl=%h result_src=%b",
                         test_name, opcode, func3, func7,
                         exp_reg_write, exp_mem_read, exp_mem_write,
                         exp_alu_src, exp_branch, exp_jump,
                         exp_alu_ctrl, exp_result_src,
                         reg_write, mem_read, mem_write, alu_src, branch, jump,
                         alu_ctrl, result_src);
                errors = errors + 1;
            end else begin
                $display("PASS: test=%s opcode=%b func3=%b func7=%b reg_write=%b mem_read=%b mem_write=%b alu_src=%b branch=%b jump=%b alu_ctrl=%h result_src=%b",
                         test_name, opcode, func3, func7,
                         reg_write, mem_read, mem_write, alu_src, branch, jump,
                         alu_ctrl, result_src);
            end
        end
    endtask

    initial begin
        $dumpfile("waves/control.vcd");
        $dumpvars(0, tb_control);

        errors = 0;

        $display("Starting control test...");

        // LUI: write immediate to rd
        opcode = LUI;
        func3 = 3'b000;
        func7 = 7'b0000000;
        check("LUI", 1'b1, 1'b0, 1'b0, 1'b0, 1'b0, 1'b0, ALU_ADD, RESULT_IMM);

        // OP / R-type ALU operations
        opcode = OP;
        func3 = ADD3;
        func7 = ADD7;
        check("OP ADD", 1'b1, 1'b0, 1'b0, 1'b0, 1'b0, 1'b0, ALU_ADD, RESULT_ALU);

        opcode = OP;
        func3 = SUB3;
        func7 = SUB7;
        check("OP SUB", 1'b1, 1'b0, 1'b0, 1'b0, 1'b0, 1'b0, ALU_SUB, RESULT_ALU);

        opcode = OP;
        func3 = SLL3;
        func7 = ADD7;
        check("OP SLL", 1'b1, 1'b0, 1'b0, 1'b0, 1'b0, 1'b0, ALU_SLL, RESULT_ALU);

        opcode = OP;
        func3 = SLT3;
        func7 = ADD7;
        check("OP SLT", 1'b1, 1'b0, 1'b0, 1'b0, 1'b0, 1'b0, ALU_SLT, RESULT_ALU);

        opcode = OP;
        func3 = SLTU3;
        func7 = ADD7;
        check("OP SLTU", 1'b1, 1'b0, 1'b0, 1'b0, 1'b0, 1'b0, ALU_SLTU, RESULT_ALU);

        opcode = OP;
        func3 = XOR3;
        func7 = ADD7;
        check("OP XOR", 1'b1, 1'b0, 1'b0, 1'b0, 1'b0, 1'b0, ALU_XOR, RESULT_ALU);

        opcode = OP;
        func3 = SRL3;
        func7 = ADD7;
        check("OP SRL", 1'b1, 1'b0, 1'b0, 1'b0, 1'b0, 1'b0, ALU_SRL, RESULT_ALU);

        opcode = OP;
        func3 = SRA3;
        func7 = SRA7;
        check("OP SRA", 1'b1, 1'b0, 1'b0, 1'b0, 1'b0, 1'b0, ALU_SRA, RESULT_ALU);

        opcode = OP;
        func3 = OR3;
        func7 = ADD7;
        check("OP OR", 1'b1, 1'b0, 1'b0, 1'b0, 1'b0, 1'b0, ALU_OR, RESULT_ALU);

        opcode = OP;
        func3 = AND3;
        func7 = ADD7;
        check("OP AND", 1'b1, 1'b0, 1'b0, 1'b0, 1'b0, 1'b0, ALU_AND, RESULT_ALU);

        // OP_IMM / I-type ALU operations
        opcode = OP_IMM;
        func3 = ADD3;
        func7 = ADD7;
        check("OP_IMM ADDI", 1'b1, 1'b0, 1'b0, 1'b1, 1'b0, 1'b0, ALU_ADD, RESULT_ALU);

        opcode = OP_IMM;
        func3 = SLL3;
        func7 = ADD7;
        check("OP_IMM SLLI", 1'b1, 1'b0, 1'b0, 1'b1, 1'b0, 1'b0, ALU_SLL, RESULT_ALU);

        opcode = OP_IMM;
        func3 = SRL3;
        func7 = ADD7;
        check("OP_IMM SRLI", 1'b1, 1'b0, 1'b0, 1'b1, 1'b0, 1'b0, ALU_SRL, RESULT_ALU);

        opcode = OP_IMM;
        func3 = SRA3;
        func7 = SRA7;
        check("OP_IMM SRAI", 1'b1, 1'b0, 1'b0, 1'b1, 1'b0, 1'b0, ALU_SRA, RESULT_ALU);

        opcode = OP_IMM;
        func3 = AND3;
        func7 = ADD7;
        check("OP_IMM ANDI", 1'b1, 1'b0, 1'b0, 1'b1, 1'b0, 1'b0, ALU_AND, RESULT_ALU);

        // LOAD / STORE
        opcode = LOAD;
        func3 = 3'b010;
        func7 = 7'b0000000;
        check("LOAD", 1'b1, 1'b1, 1'b0, 1'b1, 1'b0, 1'b0, ALU_ADD, RESULT_MEM);

        opcode = STORE;
        func3 = 3'b010;
        func7 = 7'b0000000;
        check("STORE", 1'b0, 1'b0, 1'b1, 1'b1, 1'b0, 1'b0, ALU_ADD, RESULT_ALU);

        // BRANCH comparisons
        opcode = BRANCH;
        func3 = 3'b000;
        func7 = 7'b0000000;
        check("BRANCH BEQ", 1'b0, 1'b0, 1'b0, 1'b0, 1'b1, 1'b0, ALU_SUB, RESULT_ALU);

        opcode = BRANCH;
        func3 = 3'b100;
        func7 = 7'b0000000;
        check("BRANCH BLT", 1'b0, 1'b0, 1'b0, 1'b0, 1'b1, 1'b0, ALU_SLT, RESULT_ALU);

        opcode = BRANCH;
        func3 = 3'b110;
        func7 = 7'b0000000;
        check("BRANCH BLTU", 1'b0, 1'b0, 1'b0, 1'b0, 1'b1, 1'b0, ALU_SLTU, RESULT_ALU);

        // Jumps
        opcode = JAL;
        func3 = 3'b000;
        func7 = 7'b0000000;
        check("JAL", 1'b1, 1'b0, 1'b0, 1'b0, 1'b0, 1'b1, ALU_ADD, RESULT_PC4);

        opcode = JALR;
        func3 = 3'b000;
        func7 = 7'b0000000;
        check("JALR", 1'b1, 1'b0, 1'b0, 1'b1, 1'b0, 1'b1, ALU_ADD, RESULT_PC4);

        // Unsupported opcode
        opcode = 7'b0000000;
        func3 = 3'b000;
        func7 = 7'b0000000;
        check("DEFAULT unsupported opcode", 1'b0, 1'b0, 1'b0, 1'b0, 1'b0, 1'b0, ALU_ADD, RESULT_ALU);

        if (errors == 0) begin
            $display("All control tests passed.");
        end else begin
            $display("control tests failed with %0d error(s).", errors);
        end

        $finish;
    end

endmodule

waves/control.vcd
$date
	Thu Jul  2 13:44:51 2026
$end
$version
	Icarus Verilog
$end
$timescale
	1ps
$end
$scope module tb_control $end
$var wire 2 ! result_src [1:0] $end
$var wire 1 " reg_write $end
$var wire 1 # mem_write $end
$var wire 1 $ mem_read $end
$var wire 1 % jump $end
$var wire 1 & branch $end
$var wire 1 ' alu_src $end
$var wire 4 ( alu_ctrl [3:0] $end
$var parameter 3 ) ADD3 $end
$var parameter 7 * ADD7 $end
$var parameter 4 + ALU_ADD $end
$var parameter 4 , ALU_AND $end
$var parameter 4 - ALU_OR $end
$var parameter 4 . ALU_SLL $end
$var parameter 4 / ALU_SLT $end
$var parameter 4 0 ALU_SLTU $end
$var parameter 4 1 ALU_SRA $end
$var parameter 4 2 ALU_SRL $end
$var parameter 4 3 ALU_SUB $end
$var parameter 4 4 ALU_XOR $end
$var parameter 3 5 AND3 $end
$var parameter 7 6 BRANCH $end
$var parameter 7 7 JAL $end
$var parameter 7 8 JALR $end
$var parameter 7 9 LOAD $end
$var parameter 7 : LUI $end
$var parameter 7 ; OP $end
$var parameter 7 < OP_IMM $end
$var parameter 3 = OR3 $end
$var parameter 2 > RESULT_ALU $end
$var parameter 2 ? RESULT_IMM $end
$var parameter 2 @ RESULT_MEM $end
$var parameter 2 A RESULT_PC4 $end
$var parameter 3 B SLL3 $end
$var parameter 3 C SLT3 $end
$var parameter 3 D SLTU3 $end
$var parameter 3 E SRA3 $end
$var parameter 7 F SRA7 $end
$var parameter 3 G SRL3 $end
$var parameter 7 H STORE $end
$var parameter 3 I SUB3 $end
$var parameter 7 J SUB7 $end
$var parameter 3 K XOR3 $end
$var reg 3 L func3 [2:0] $end
$var reg 7 M func7 [6:0] $end
$var reg 7 N opcode [6:0] $end
$var integer 32 O errors [31:0] $end
$scope module dut $end
$var wire 3 P func3 [2:0] $end
$var wire 7 Q func7 [6:0] $end
$var wire 7 R opcode [6:0] $end
$var parameter 3 S ADD3 $end
$var parameter 7 T ADD7 $end
$var parameter 4 U ALU_ADD $end
$var parameter 4 V ALU_AND $end
$var parameter 4 W ALU_OR $end
$var parameter 4 X ALU_SLL $end
$var parameter 4 Y ALU_SLT $end
$var parameter 4 Z ALU_SLTU $end
$var parameter 4 [ ALU_SRA $end
$var parameter 4 \ ALU_SRL $end
$var parameter 4 ] ALU_SUB $end
$var parameter 4 ^ ALU_XOR $end
$var parameter 3 _ AND3 $end
$var parameter 7 ` AND7 $end
$var parameter 3 a BEQ3 $end
$var parameter 3 b BGE3 $end
$var parameter 3 c BGEU3 $end
$var parameter 3 d BLT3 $end
$var parameter 3 e BLTU3 $end
$var parameter 3 f BNE3 $end
$var parameter 7 g BRANCH $end
$var parameter 7 h JAL $end
$var parameter 7 i JALR $end
$var parameter 7 j LOAD $end
$var parameter 7 k LUI $end
$var parameter 7 l OP $end
$var parameter 7 m OP_IMM $end
$var parameter 3 n OR3 $end
$var parameter 7 o OR7 $end
$var parameter 2 p RESULT_ALU $end
$var parameter 2 q RESULT_IMM $end
$var parameter 2 r RESULT_MEM $end
$var parameter 2 s RESULT_PC4 $end
$var parameter 3 t SLL3 $end
$var parameter 7 u SLL7 $end
$var parameter 3 v SLT3 $end
$var parameter 7 w SLT7 $end
$var parameter 3 x SLTU3 $end
$var parameter 7 y SLTU7 $end
$var parameter 3 z SRA3 $end
$var parameter 7 { SRA7 $end
$var parameter 3 | SRL3 $end
$var parameter 7 } SRL7 $end
$var parameter 7 ~ STORE $end
$var parameter 3 !" SUB3 $end
$var parameter 7 "" SUB7 $end
$var parameter 3 #" XOR3 $end
$var parameter 7 $" XOR7 $end
$var reg 4 %" alu_ctrl [3:0] $end
$var reg 1 ' alu_src $end
$var reg 1 & branch $end
$var reg 1 % jump $end
$var reg 1 $ mem_read $end
$var reg 1 # mem_write $end
$var reg 1 " reg_write $end
$var reg 2 &" result_src [1:0] $end
$upscope $end
$scope task check $end
$var reg 4 '" exp_alu_ctrl [3:0] $end
$var reg 1 (" exp_alu_src $end
$var reg 1 )" exp_branch $end
$var reg 1 *" exp_jump $end
$var reg 1 +" exp_mem_read $end
$var reg 1 ," exp_mem_write $end
$var reg 1 -" exp_reg_write $end
$var reg 2 ." exp_result_src [1:0] $end
$var reg 256 /" test_name [255:0] $end
$upscope $end
$upscope $end
$enddefinitions $end
$comment Show the parameter values. $end
$dumpall
b0 $"
b100 #"
b100000 ""
b0 !"
b100011 ~
b0 }
b101 |
b100000 {
b101 z
b0 y
b11 x
b0 w
b10 v
b0 u
b1 t
b10 s
b1 r
b11 q
b0 p
b0 o
b110 n
b10011 m
b110011 l
b110111 k
b11 j
b1100111 i
b1101111 h
b1100011 g
b1 f
b110 e
b100 d
b111 c
b101 b
b0 a
b0 `
b111 _
b100 ^
b1 ]
b110 \
b111 [
b1001 Z
b1000 Y
b101 X
b11 W
b10 V
b0 U
b0 T
b0 S
b100 K
b100000 J
b0 I
b100011 H
b101 G
b100000 F
b101 E
b11 D
b10 C
b1 B
b10 A
b1 @
b11 ?
b0 >
b110 =
b10011 <
b110011 ;
b110111 :
b11 9
b1100111 8
b1101111 7
b1100011 6
b111 5
b100 4
b1 3
b110 2
b111 1
b1001 0
b1000 /
b101 .
b11 -
b10 ,
b0 +
b0 *
b0 )
$end
#0
$dumpvars
b10011000101010101001001 /"
b11 ."
1-"
0,"
0+"
0*"
0)"
0("
b0 '"
b11 &"
b0 %"
b110111 R
b0 Q
b0 P
b0 O
b110111 N
b0 M
b0 L
b0 (
0'
0&
0%
0$
0#
1"
b11 !
$end
#1000
b0 !
b0 &"
1"
b0 ."
b10011110101000000100000010000010100010001000100 /"
b110011 N
b110011 R
#2000
b1 (
b1 %"
1"
b1 '"
b10011110101000000100000010100110101010101000010 /"
b100000 M
b100000 Q
#3000
b101 (
b101 %"
1"
b101 '"
b10011110101000000100000010100110100110001001100 /"
b0 M
b0 Q
b1 L
b1 P
#4000
b1000 (
b1000 %"
1"
b1000 '"
b10011110101000000100000010100110100110001010100 /"
b10 L
b10 P
#5000
b1001 (
b1001 %"
1"
b1001 '"
b1001111010100000010000001010011010011000101010001010101 /"
b11 L
b11 P
#6000
b100 (
b100 %"
1"
b100 '"
b10011110101000000100000010110000100111101010010 /"
b100 L
b100 P
#7000
b110 (
b110 %"
1"
b110 '"
b10011110101000000100000010100110101001001001100 /"
b101 L
b101 P
#8000
b111 (
b111 %"
1"
b111 '"
b10011110101000000100000010100110101001001000001 /"
b100000 M
b100000 Q
#9000
b11 (
b11 %"
1"
b11 '"
b100111101010000001000000100111101010010 /"
b0 M
b0 Q
b110 L
b110 P
#10000
b10 (
b10 %"
1"
b10 '"
b10011110101000000100000010000010100111001000100 /"
b111 L
b111 P
#11000
1'
b0 (
b0 %"
1"
b0 '"
1("
b100111101010000010111110100100101001101010011010010000001000001010001000100010001001001 /"
b0 L
b0 P
b10011 N
b10011 R
#12000
b101 (
b101 %"
1'
1"
b101 '"
b100111101010000010111110100100101001101010011010010000001010011010011000100110001001001 /"
b1 L
b1 P
#13000
b110 (
b110 %"
1'
1"
b110 '"
b100111101010000010111110100100101001101010011010010000001010011010100100100110001001001 /"
b101 L
b101 P
#14000
b111 (
b111 %"
1'
1"
b111 '"
b100111101010000010111110100100101001101010011010010000001010011010100100100000101001001 /"
b100000 M
b100000 Q
#15000
b10 (
b10 %"
1'
1"
b10 '"
b100111101010000010111110100100101001101010011010010000001000001010011100100010001001001 /"
b0 M
b0 Q
b111 L
b111 P
#16000
b1 !
b1 &"
1$
b0 (
b0 %"
1'
1"
b1 ."
b0 '"
1+"
b1001100010011110100000101000100 /"
b10 L
b10 P
b11 N
b11 R
#17000
1#
b0 !
b0 &"
1'
0$
0"
b0 ."
1,"
0+"
0-"
b101001101010100010011110101001001000101 /"
b100011 N
b100011 R
#18000
b1 (
b1 %"
1&
0'
0#
b1 '"
1)"
0("
0,"
b1000010010100100100000101001110010000110100100000100000010000100100010101010001 /"
b0 L
b0 P
b1100011 N
b1100011 R
#19000
b1000 (
b1000 %"
1&
b1000 '"
b1000010010100100100000101001110010000110100100000100000010000100100110001010100 /"
b100 L
b100 P
#20000
b1001 (
b1001 %"
1&
b1001 '"
b100001001010010010000010100111001000011010010000010000001000010010011000101010001010101 /"
b110 L
b110 P
#21000
b10 !
b10 &"
1%
1"
b0 (
b0 %"
0&
b10 ."
b0 '"
1*"
0)"
1-"
b10010100100000101001100 /"
b0 L
b0 P
b1101111 N
b1101111 R
#22000
1'
b10 !
b10 &"
1%
1"
1("
b1001010010000010100110001010010 /"
b1100111 N
b1100111 R
#23000
b0 !
b0 &"
0%
0'
0"
b0 ."
0*"
0("
0-"
b100010001000101010001100100000101010101010011000101010000100000011101010110111001110011011101010111000001110000011011110111001001110100011001010110010000100000011011110111000001100011011011110110010001100101 /"
b0 N
b0 R
