rtl/data_mem.v
module data_mem(
    input clk,
    input reset,
    input mem_read,
    input mem_write,
    input [31:0] addr,
    input [31:0] write_data,
    output [31:0] read_data
);
    reg [31:0] mem [0:511];

    assign read_data = mem_read ? mem[addr[10:2]] : 32'b0;

    integer i;

    always @(posedge clk) begin
        if (reset) begin
            for (i = 0; i < 512; i = i + 1) begin
                mem[i] <= 32'd0;
            end
        end else if (mem_write) begin
            mem[addr[10:2]] <= write_data;
        end
    end
endmodule

rtl/alu.v
module alu(
    input [31:0]a, 
    input [31:0]b, 
    input [3:0]alu_ctrl, 
    output reg [31:0]out, 
    output reg zero, 
    output reg carry, 
    output reg overflow, 
    output reg negative
    );
    
    reg [32:0]temp;

    always @(*) begin
        // default
        out = 32'b0;
        zero = 1'b0;
        carry = 1'b0;
        overflow = 1'b0;
        negative = 1'b0;
        temp = 33'b0;

        case(alu_ctrl)
            4'h0: begin                                             // add
                temp = {1'b0, a} + {1'b0, b};
                out = temp[31:0];
                carry = temp[32];

                // signed overflow for addition
                overflow = (a[31] == b[31]) && (out[31] != a[31]);
            end
            4'h1: begin   
                temp = {1'b0, a} - {1'b0, b};                       // sub
                out = temp[31:0];

                // carry = 1 when no borrow
                carry = (a >= b);

                // signed overflow for subtraction
                overflow = (a[31] != b[31]) && (out[31] != a[31]);
            end
            4'h2: out = a & b;                                      // and
            4'h3: out = a | b;                                      // or
            4'h4: out = a ^ b;                                      // xor
            4'h5: out = a << b[4:0];                                // sll
            4'h6: out = a >> b[4:0];                                // srl
            4'h7: out = $signed(a) >>> b[4:0];                      // sra
            4'h8: out = ($signed(a) < $signed(b)) ? 32'h1 : 32'h0;  // slt
            4'h9: out = (a < b) ? 32'h1 : 32'h0;                    // sltu
            default: out = 32'b0;
        endcase

        // set zero & negative
        zero = (out == 32'b0);
        negative = out[31];
    end
endmodule

rtl/imm_gen.v
module imm_gen(
    input [31:0] instr,
    output reg [31:0] imm
);
    // https://msyksphinz-self.github.io/riscv-isadoc/
    wire [6:0] opcode;
    assign opcode = instr[6:0];

    // opcode
    localparam LUI      = 7'b0110111; // lui
    localparam OP_IMM   = 7'b0010011; // addi, slti, xori, ... 
    localparam LOAD     = 7'b0000011; // lb, lbu, lh, lhu, lw
    localparam STORE    = 7'b0100011; // sb, sh, sw
    localparam BRANCH   = 7'b1100011; // beq, bne, blt, bge, bltu, bgeu
    localparam JAL      = 7'b1101111; // jal
    localparam JALR     = 7'b1100111; // jalr

    always @(*) begin
        case(opcode)
            LUI: begin
                imm = {{20{instr[31]}}, instr[31:12]};
            end
            OP_IMM, LOAD: begin
                imm = {{20{instr[31]}}, instr[31:20]};
            end
            STORE: begin
                imm = {{20{instr[31]}}, instr[31:25], instr[11:7]};
            end
            BRANCH: begin
                imm = {{19{instr[31]}}, instr[31], instr[7], instr[30:25], instr[11:8], 1'b0};
            end
            JAL: begin
                imm = {{11{instr[31]}}, instr[31], instr[19:12], instr[20], instr[30:21], 1'b0};
            end
            JALR: begin
                imm = {{20{instr[31]}}, instr[31:20]};
            end
            default: imm = 32'd0;
        endcase
    end

endmodule

rtl/control.v
module control (
    input [6:0] opcode,
    input [2:0] func3,
    input [6:0] func7,
    output reg reg_write,
    output reg mem_read,
    output reg mem_write,
    output reg alu_src,         // 0 = rv2, 1 = imm
    output reg branch,
    output reg jump,
    output reg [3:0] alu_ctrl,  // 0 = add, 1 = sub, ... 
    output reg [1:0] result_src // 00 = ALU result, 01 = mem read data, 10 = PC + 4, 11 = imm
);
    // opcode
    localparam LUI      = 7'b0110111; // lui
    localparam OP       = 7'b0110011; // add, sub, ...
    localparam OP_IMM   = 7'b0010011; // addi, slti, xori, ... 
    localparam LOAD     = 7'b0000011; // lb, lbu, lh, lhu, lw
    localparam STORE    = 7'b0100011; // sb, sh, sw
    localparam BRANCH   = 7'b1100011; // beq, bne, blt, bge, bltu, bgeu
    localparam JAL      = 7'b1101111; // jal
    localparam JALR     = 7'b1100111; // jalr

    // func3
    localparam ADD3     = 3'b000;
    localparam SUB3     = ADD3;
    localparam SLL3     = 3'b001;
    localparam SLT3     = 3'b010;
    localparam SLTU3    = 3'b011;
    localparam XOR3     = 3'b100;
    localparam SRL3     = 3'b101;
    localparam SRA3     = SRL3;
    localparam OR3      = 3'b110;
    localparam AND3     = 3'b111;

    localparam BEQ3     = ADD3;
    localparam BNE3     = SLL3;
    localparam BLT3     = XOR3;
    localparam BGE3     = SRL3;
    localparam BLTU3    = OR3;
    localparam BGEU3    = AND3;

    // func7
    localparam ADD7     = 7'b0000000;
    localparam SLL7     = ADD7;
    localparam SLT7     = ADD7;
    localparam SLTU7    = ADD7;
    localparam XOR7     = ADD7;
    localparam SRL7     = ADD7;
    localparam OR7      = ADD7;
    localparam AND7     = ADD7;
    localparam SUB7     = 7'b0100000;
    localparam SRA7     = SUB7;

    // alu_ctrl
    localparam ALU_ADD  = 4'h0;
    localparam ALU_SUB  = 4'h1;
    localparam ALU_AND  = 4'h2;
    localparam ALU_OR   = 4'h3;
    localparam ALU_XOR  = 4'h4;
    localparam ALU_SLL  = 4'h5;
    localparam ALU_SRL  = 4'h6;
    localparam ALU_SRA  = 4'h7;
    localparam ALU_SLT  = 4'h8;
    localparam ALU_SLTU = 4'h9;

    // result_src
    localparam RESULT_ALU = 2'b00;
    localparam RESULT_MEM = 2'b01;
    localparam RESULT_PC4 = 2'b10;
    localparam RESULT_IMM = 2'b11;

    always @(*) begin
        reg_write   = 1'b0;
        mem_read    = 1'b0;
        mem_write   = 1'b0;
        alu_src     = 1'b0;
        branch      = 1'b0;
        jump        = 1'b0;
        alu_ctrl    = ALU_ADD;
        result_src  = RESULT_ALU;

        case(opcode)
            LUI: begin
                reg_write   = 1'b1;
                result_src  = RESULT_IMM;
            end
            OP: begin
                reg_write   = 1'b1;
                alu_src     = 1'b0;

                case({func7, func3})
                    {ADD7, ADD3}:   alu_ctrl = ALU_ADD;
                    {SUB7, SUB3}:   alu_ctrl = ALU_SUB;
                    {SLL7, SLL3}:   alu_ctrl = ALU_SLL;
                    {SLT7, SLT3}:   alu_ctrl = ALU_SLT;
                    {SLTU7, SLTU3}: alu_ctrl = ALU_SLTU;
                    {XOR7, XOR3}:   alu_ctrl = ALU_XOR;
                    {SRL7, SRL3}:   alu_ctrl = ALU_SRL;
                    {SRA7, SRA3}:   alu_ctrl = ALU_SRA;
                    {OR7, OR3}:     alu_ctrl = ALU_OR;
                    {AND7, AND3}:   alu_ctrl = ALU_AND;
                    default:        alu_ctrl = ALU_ADD;
                endcase
            end
            OP_IMM: begin
                reg_write   = 1'b1;
                alu_src     = 1'b1;

                case(func3)
                    ADD3:    alu_ctrl = ALU_ADD;
                    SLL3:    alu_ctrl = ALU_SLL;
                    SLT3:    alu_ctrl = ALU_SLT;
                    SLTU3:   alu_ctrl = ALU_SLTU;
                    XOR3:    alu_ctrl = ALU_XOR;
                    SRL3:    alu_ctrl = (func7 == SRA7) ? ALU_SRA : ALU_SRL;
                    OR3:     alu_ctrl = ALU_OR;
                    AND3:    alu_ctrl = ALU_AND;
                    default: alu_ctrl = ALU_ADD;
                endcase
            end
            LOAD: begin
                reg_write   = 1'b1;
                mem_read    = 1'b1;
                alu_src     = 1'b1;
                alu_ctrl    = ALU_ADD;
                result_src  = RESULT_MEM;
            end
            STORE: begin
                mem_write   = 1'b1;
                alu_src     = 1'b1;
                alu_ctrl    = ALU_ADD;
            end
            BRANCH: begin
                branch      = 1'b1;

                case(func3)
                    BEQ3, BNE3:   alu_ctrl = ALU_SUB;
                    BLT3, BGE3:   alu_ctrl = ALU_SLT;
                    BLTU3, BGEU3: alu_ctrl = ALU_SLTU;
                    default:      alu_ctrl = ALU_SUB;
                endcase
            end
            JAL: begin
                reg_write   = 1'b1;
                jump        = 1'b1;
                result_src  = RESULT_PC4;
            end
            JALR: begin
                reg_write   = 1'b1;
                alu_src     = 1'b1;
                jump        = 1'b1;
                alu_ctrl    = ALU_ADD;
                result_src  = RESULT_PC4;
            end
            default: begin
            end
        endcase
    end

endmodule

rtl/regfile.v
module regfile(
    input clk, 
    input reset,
    input w_en,             // regfile allowed to write when w_en = 1
    input  [4:0] rs1,        // 32 registers --> 5 bits
    input  [4:0] rs2, 
    input  [4:0] rd, 
    input  [31:0] w_data,    // write data
    output [31:0] rv1,       // read value (of rs1)
    output [31:0] rv2        // read value (of rs2)
    );

    reg [31:0] regs [0:31]; // 32-bit registers * 32

    assign rv1 = (rs1 == 5'd0) ? 32'd0 : regs[rs1]; // rv1 = 0 if rs1 = x0
    assign rv2 = (rs2 == 5'd0) ? 32'd0 : regs[rs2]; // rv2 = 0 if rs2 = x0

    integer i;

    always @(posedge clk) begin
        if (reset) begin
            for (i = 0; i < 32; i = i + 1) begin
                regs[i] <= 32'd0;
            end
        end else if (w_en && rd != 5'd0) begin
            regs[rd] <= w_data;     // write w_data into regs[rd]
        end
    
    end
    
endmodule

rtl/instr_mem.v
module instr_mem(
    input [31:0] pc,
    output [31:0] instr
);
    reg [31:0] mem [0:511]; // 2KB instruction space
    
    integer i;

    initial begin
        for (i = 0; i < 512; i = i + 1) begin
            mem[i] = 32'h00000013; // nop: addi x0, x0, 0
        end

        $readmemh("tb/programs/cpu_test.hex", mem);
    end

    assign instr = mem[pc[10:2]]; // 9 bits of PC

endmodule

rtl/pc.v
module pc(
    input clk,
    input reset,
    input branch,
    input jump,
    input [31:0] imm,
    output reg [31:0] pc
);

    always @(posedge clk) begin
        if (reset) begin
            pc <= 32'h0;
        end else if (jump || branch) begin
            pc <= pc += imm;
        end else begin
            pc <= pc += 32'd4;
        end
    end

endmodule

rtl/cpu.v
module cpu(
    input clk,
    input reset
);

    // pc
    wire [31:0] pc_curr;
    wire [31:0] instr;
    wire [31:0] pc_plus_4;

    assign pc_plus_4 = pc_curr + 32'd4;

    // Instruction
    wire [6:0] opcode;
    wire [2:0] func3;
    wire [6:0] func7;
    wire [4:0] rd;
    wire [4:0] rs1;
    wire [4:0] rs2;

    assign opcode = instr[6:0];
    assign func3 = instr[14:12];
    assign func7 = instr[31:25];
    assign rd = instr[11:7];
    assign rs1 = instr[19:15];
    assign rs2 = instr[24:20];

    // Control
    wire reg_write;
    wire mem_read;
    wire mem_write;
    wire alu_src;
    wire branch;
    wire jump;
    wire [3:0] alu_ctrl;
    wire [1:0] result_src;

    // Regfile
    wire [31:0] rv1;
    wire [31:0] rv2;
    wire [31:0] w_data;

    // imm_gen
    wire [31:0] imm;

    // ALU
    wire [31:0] a;
    wire [31:0] b;
    wire [31:0] out;
    wire zero;
    wire carry;
    wire overflow;
    wire negative;

    assign a = rv1;
    assign b = alu_src ? imm : rv2;

    // data_mem
    wire [31:0] addr;
    wire [31:0] write_data;
    wire [31:0] read_data;

    assign addr = out;
    assign write_data = rv2;

    // Branch condition true or not
    reg branch_taken;
    always @(*) begin
        case (func3)
            3'b000: branch_taken = branch && (rs1 == rs2); // beq
            3'b001: branch_taken = branch && (rs1 != rs2); // bne
            3'b100: branch_taken = branch && ($signed(rs1) < $signed(rs2)); // blt
            3'b101: branch_taken = branch && ($signed(rs1) >= $signed(rs2)); // bge
            default: branch_taken = 1'b0;
        endcase
    end
    
    // pc
    pc pc_instr (
        .clk(clk),
        .reset(reset),
        .branch(branch_taken),
        .jump(jump),
        .imm(imm),
        .pc(pc_curr)
    );

    // instr_mem
    instr_mem imem (
        .pc(pc_curr),
        .instr(instr)
    );

    // regfile
    regfile rf (
        .clk(clk),
        .reset(reset),
        .w_en(reg_write),
        .rs1(rs1),
        .rs2(rs2),
        .rd(rd),
        .w_data(w_data),
        .rv1(rv1),
        .rv2(rv2)
    );

    // control
    control ctrl (
        .opcode(opcode),
        .func3(func3),
        .func7(func7),
        .reg_write(reg_write),
        .mem_read(mem_read),
        .mem_write(mem_write),
        .alu_src(alu_src),
        .branch(branch),
        .jump(jump),
        .alu_ctrl(alu_ctrl),
        .result_src(result_src)
    );

    // imm_gen
    imm_gen igen (
        .instr(instr),
        .imm(imm)
    );

    // ALU
    alu alu_mod (
        .a(a),
        .b(b),
        .alu_ctrl(alu_ctrl),
        .out(out),
        .zero(zero),
        .carry(carry),
        .overflow(overflow),
        .negative(negative)
    );

    // data_mem
    data_mem dmem (
        .clk(clk),
        .reset(reset),
        .mem_read(mem_read),
        .mem_write(mem_write),
        .addr(addr),
        .write_data(write_data),
        .read_data(read_data)
    );
    
    // write back in regfile
    assign w_data = 
        (result_src == 2'b00) ? out :
        (result_src == 2'b01) ? read_data :
        (result_src == 2'b10) ? pc_plus_4 :
        (result_src == 2'b11) ? imm :
        32'd0;

endmodule

tb/tb_cpu.v
`timescale 1ns / 1ps

module tb_cpu;
    reg clk;
    reg reset;

    integer errors;

    cpu dut (
        .clk(clk),
        .reset(reset)
    );

    always begin
        #5 clk = ~clk;
    end

    task check;
        input [127:0] test_name;
        input [31:0] actual;
        input [31:0] expected;
        begin
            #1;
            if (actual !== expected) begin
                $display("FAIL: mem/reg=%s expected = %h, got = %h",
                         test_name, expected, actual);
                errors = errors + 1;
            end else begin
                $display("PASS: mem/reg=%s got = %h",
                         test_name, actual);
            end
        end
    endtask

    initial begin
        $dumpfile("waves/cpu.vcd");
        $dumpvars(0, tb_cpu);

        errors = 0;
        clk = 0;
        reset = 1'b1;

        $display("Starting CPU test...");

        @(posedge clk)
        #1;
        reset = 0;

        // Test 1: instructions 1-4
        /*
         * addi x1, x0, 5
         * addi x2, x0, 4
         * add  x3, x1, x2
         * sw   x3, 0(x0)
        */
        repeat(4) begin
            @(posedge clk);
        end

        check("x1", dut.rf.regs[1], 32'd5);
        check("x2", dut.rf.regs[2], 32'd4);
        check("x3", dut.rf.regs[3], 32'd9);
        check("mem[0]", dut.dmem.mem[0], 32'd9);

        // Test 2: instructions 5-8
        /*
         * addi x1, x1, -3
         * lw   x2, 0(x0)
         * sub  x3, x2, x1
         * sw   x3, 4(x0)
        */
        repeat(4) begin
            @(posedge clk);
        end

        check("x1", dut.rf.regs[1], 32'd2);
        check("x2", dut.rf.regs[2], 32'd9);
        check("x3", dut.rf.regs[3], 32'd7);
        check("mem[1]", dut.dmem.mem[1], 32'd7);

        // Test 3: instructions 9-16
        /*
         * addi x4, x0, 15
         * addi x5, x0, 10
         * and  x6, x4, x5
         * or   x7, x4, x5
         * xor  x8, x4, x5
         * sw   x6, 8(x0)
         * sw   x7, 12(x0)
         * sw   x8, 16(x0)
        */
        repeat(8) begin
            @(posedge clk);
        end

        check("x4", dut.rf.regs[4], 32'd15);
        check("x5", dut.rf.regs[5], 32'd10);
        check("x6", dut.rf.regs[6], 32'd10);
        check("x7", dut.rf.regs[7], 32'd15);
        check("x8", dut.rf.regs[8], 32'd5);
        check("mem[2]", dut.dmem.mem[2], 32'd10);
        check("mem[3]", dut.dmem.mem[3], 32'd15);
        check("mem[4]", dut.dmem.mem[4], 32'd5);

        // NOPs to check if padding is harmless
        repeat(4) begin
            @(posedge clk);
        end

        check("x1 final", dut.rf.regs[1], 32'd2);
        check("x8 final", dut.rf.regs[8], 32'd5);
        check("mem[4] final", dut.dmem.mem[4], 32'd5);

        // FINAL
        if (errors == 0) begin
            $display("ALL CPU TESTS PASSED");
        end else begin
            $display("CPU TESTS FAILED: %d errors", errors);
        end

        $finish;
    end

endmodule

waves/cpu.vcd
$date
	Fri Jul 10 12:44:01 2026
$end
$version
	Icarus Verilog
$end
$timescale
	1ps
$end
$scope module tb_cpu $end
$var reg 1 ! clk $end
$var reg 1 " reset $end
$var integer 32 # errors [31:0] $end
$scope module dut $end
$var wire 32 $ a [31:0] $end
$var wire 32 % addr [31:0] $end
$var wire 1 ! clk $end
$var wire 1 " reset $end
$var wire 32 & write_data [31:0] $end
$var wire 1 ' zero $end
$var wire 32 ( w_data [31:0] $end
$var wire 32 ) rv2 [31:0] $end
$var wire 32 * rv1 [31:0] $end
$var wire 5 + rs2 [4:0] $end
$var wire 5 , rs1 [4:0] $end
$var wire 2 - result_src [1:0] $end
$var wire 1 . reg_write $end
$var wire 32 / read_data [31:0] $end
$var wire 5 0 rd [4:0] $end
$var wire 32 1 pc_plus_4 [31:0] $end
$var wire 32 2 pc_curr [31:0] $end
$var wire 1 3 overflow $end
$var wire 32 4 out [31:0] $end
$var wire 7 5 opcode [6:0] $end
$var wire 1 6 negative $end
$var wire 1 7 mem_write $end
$var wire 1 8 mem_read $end
$var wire 1 9 jump $end
$var wire 32 : instr [31:0] $end
$var wire 32 ; imm [31:0] $end
$var wire 7 < func7 [6:0] $end
$var wire 3 = func3 [2:0] $end
$var wire 1 > carry $end
$var wire 1 ? branch $end
$var wire 32 @ b [31:0] $end
$var wire 1 A alu_src $end
$var wire 4 B alu_ctrl [3:0] $end
$var reg 1 C branch_taken $end
$scope module alu_mod $end
$var wire 32 D a [31:0] $end
$var wire 32 E b [31:0] $end
$var wire 4 F alu_ctrl [3:0] $end
$var reg 1 > carry $end
$var reg 1 6 negative $end
$var reg 32 G out [31:0] $end
$var reg 1 3 overflow $end
$var reg 33 H temp [32:0] $end
$var reg 1 ' zero $end
$upscope $end
$scope module ctrl $end
$var wire 3 I func3 [2:0] $end
$var wire 7 J func7 [6:0] $end
$var wire 7 K opcode [6:0] $end
$var parameter 3 L ADD3 $end
$var parameter 7 M ADD7 $end
$var parameter 4 N ALU_ADD $end
$var parameter 4 O ALU_AND $end
$var parameter 4 P ALU_OR $end
$var parameter 4 Q ALU_SLL $end
$var parameter 4 R ALU_SLT $end
$var parameter 4 S ALU_SLTU $end
$var parameter 4 T ALU_SRA $end
$var parameter 4 U ALU_SRL $end
$var parameter 4 V ALU_SUB $end
$var parameter 4 W ALU_XOR $end
$var parameter 3 X AND3 $end
$var parameter 7 Y AND7 $end
$var parameter 3 Z BEQ3 $end
$var parameter 3 [ BGE3 $end
$var parameter 3 \ BGEU3 $end
$var parameter 3 ] BLT3 $end
$var parameter 3 ^ BLTU3 $end
$var parameter 3 _ BNE3 $end
$var parameter 7 ` BRANCH $end
$var parameter 7 a JAL $end
$var parameter 7 b JALR $end
$var parameter 7 c LOAD $end
$var parameter 7 d LUI $end
$var parameter 7 e OP $end
$var parameter 7 f OP_IMM $end
$var parameter 3 g OR3 $end
$var parameter 7 h OR7 $end
$var parameter 2 i RESULT_ALU $end
$var parameter 2 j RESULT_IMM $end
$var parameter 2 k RESULT_MEM $end
$var parameter 2 l RESULT_PC4 $end
$var parameter 3 m SLL3 $end
$var parameter 7 n SLL7 $end
$var parameter 3 o SLT3 $end
$var parameter 7 p SLT7 $end
$var parameter 3 q SLTU3 $end
$var parameter 7 r SLTU7 $end
$var parameter 3 s SRA3 $end
$var parameter 7 t SRA7 $end
$var parameter 3 u SRL3 $end
$var parameter 7 v SRL7 $end
$var parameter 7 w STORE $end
$var parameter 3 x SUB3 $end
$var parameter 7 y SUB7 $end
$var parameter 3 z XOR3 $end
$var parameter 7 { XOR7 $end
$var reg 4 | alu_ctrl [3:0] $end
$var reg 1 A alu_src $end
$var reg 1 ? branch $end
$var reg 1 9 jump $end
$var reg 1 8 mem_read $end
$var reg 1 7 mem_write $end
$var reg 1 . reg_write $end
$var reg 2 } result_src [1:0] $end
$upscope $end
$scope module dmem $end
$var wire 32 ~ addr [31:0] $end
$var wire 1 ! clk $end
$var wire 1 8 mem_read $end
$var wire 1 7 mem_write $end
$var wire 1 " reset $end
$var wire 32 !" write_data [31:0] $end
$var wire 32 "" read_data [31:0] $end
$var integer 32 #" i [31:0] $end
$upscope $end
$scope module igen $end
$var wire 7 $" opcode [6:0] $end
$var wire 32 %" instr [31:0] $end
$var parameter 7 &" BRANCH $end
$var parameter 7 '" JAL $end
$var parameter 7 (" JALR $end
$var parameter 7 )" LOAD $end
$var parameter 7 *" LUI $end
$var parameter 7 +" OP_IMM $end
$var parameter 7 ," STORE $end
$var reg 32 -" imm [31:0] $end
$upscope $end
$scope module imem $end
$var wire 32 ." instr [31:0] $end
$var wire 32 /" pc [31:0] $end
$var integer 32 0" i [31:0] $end
$upscope $end
$scope module pc_instr $end
$var wire 1 C branch $end
$var wire 1 ! clk $end
$var wire 32 1" imm [31:0] $end
$var wire 1 9 jump $end
$var wire 1 " reset $end
$var reg 32 2" pc [31:0] $end
$upscope $end
$scope module rf $end
$var wire 1 ! clk $end
$var wire 5 3" rd [4:0] $end
$var wire 1 " reset $end
$var wire 5 4" rs1 [4:0] $end
$var wire 5 5" rs2 [4:0] $end
$var wire 32 6" w_data [31:0] $end
$var wire 1 . w_en $end
$var wire 32 7" rv2 [31:0] $end
$var wire 32 8" rv1 [31:0] $end
$var integer 32 9" i [31:0] $end
$upscope $end
$upscope $end
$scope task check $end
$var reg 32 :" actual [31:0] $end
$var reg 32 ;" expected [31:0] $end
$var reg 128 <" test_name [127:0] $end
$upscope $end
$upscope $end
$enddefinitions $end
$comment Show the parameter values. $end
$dumpall
b100011 ,"
b10011 +"
b110111 *"
b11 )"
b1100111 ("
b1101111 '"
b1100011 &"
b0 {
b100 z
b100000 y
b0 x
b100011 w
b0 v
b101 u
b100000 t
b101 s
b0 r
b11 q
b0 p
b10 o
b0 n
b1 m
b10 l
b1 k
b11 j
b0 i
b0 h
b110 g
b10011 f
b110011 e
b110111 d
b11 c
b1100111 b
b1101111 a
b1100011 `
b1 _
b110 ^
b100 ]
b111 \
b101 [
b0 Z
b0 Y
b111 X
b100 W
b1 V
b110 U
b111 T
b1001 S
b1000 R
b101 Q
b11 P
b10 O
b0 N
b0 M
b0 L
$end
#0
$dumpvars
bx <"
bx ;"
bx :"
bx 9"
bx 8"
bx 7"
bx 6"
bx 5"
bx 4"
bx 3"
bx 2"
bx 1"
b1000000000 0"
bx /"
bx ."
bx -"
bx %"
bx $"
bx #"
bx ""
bx !"
bx ~
bx }
bx |
bx K
bx J
bx I
bx H
bx G
bx F
bx E
bx D
xC
bx B
xA
bx @
x?
x>
bx =
bx <
bx ;
bx :
x9
x8
x7
x6
bx 5
bx 4
x3
bx 2
bx 1
bx 0
bx /
x.
bx -
bx ,
bx +
bx *
bx )
bx (
x'
bx &
bx %
bx $
b0 #
1"
0!
$end
#5000
b101 (
b101 6"
b101 H
06
03
0>
0'
b101 %
b101 ~
b101 4
b101 G
b101 @
b101 E
b0 /
b0 ""
b0 &
b0 !"
b0 )
b0 7"
b0 $
b0 D
b0 *
b0 8"
0C
b0 -
b0 }
b0 B
b0 F
b0 |
09
0?
1A
07
08
1.
b10011 $"
b101 +
b101 5"
b0 ,
b0 4"
b1 0
b1 3"
b0 <
b0 J
b0 =
b0 I
b10011 5
b10011 K
b101 ;
b101 -"
b101 1"
b10100000000000010010011 :
b10100000000000010010011 %"
b10100000000000010010011 ."
b100 1
b0 2
b0 /"
b0 2"
b100000 9"
b1000000000 #"
1!
#6000
0"
#10000
0!
#15000
b100 (
b100 6"
b100 H
b100 %
b100 ~
b100 4
b100 G
b100 @
b100 E
b100 +
b100 5"
b10 0
b10 3"
b100 ;
b100 -"
b100 1"
b10000000000000100010011 :
b10000000000000100010011 %"
b10000000000000100010011 ."
b1000 1
b100 2
b100 /"
b100 2"
1!
#20000
0!
#25000
b1001 (
b1001 6"
b100 &
b100 !"
b100 )
b100 7"
b1001 H
b1001 %
b1001 ~
b1001 4
b1001 G
b101 $
b101 D
b101 *
b101 8"
0A
1.
b100 @
b100 E
b110011 $"
b10 +
b10 5"
b1 ,
b1 4"
b11 0
b11 3"
b110011 5
b110011 K
b0 ;
b0 -"
b0 1"
b1000001000000110110011 :
b1000001000000110110011 %"
b1000001000000110110011 ."
b1100 1
b1000 2
b1000 /"
b1000 2"
1!
#30000
0!
#35000
b0 (
b0 6"
b1001 &
b1001 !"
b1001 )
b1001 7"
1'
b0 H
b0 %
b0 ~
b0 4
b0 G
b0 @
b0 E
b0 $
b0 D
b0 *
b0 8"
1A
17
0.
b100011 $"
b11 +
b11 5"
b0 ,
b0 4"
b0 0
b0 3"
b10 =
b10 I
b100011 5
b100011 K
b1100000010000000100011 :
b1100000010000000100011 %"
b1100000010000000100011 ."
b10000 1
b1100 2
b1100 /"
b1100 2"
1!
#40000
0!
#45000
1>
b10 (
b10 6"
b0 &
b0 !"
b0 )
b0 7"
06
b10 %
b10 ~
b10 4
b10 G
b100000000000000000000000000000010 H
0'
b101 $
b101 D
b101 *
b101 8"
1.
1A
07
b11111111111111111111111111111101 @
b11111111111111111111111111111101 E
b10011 $"
b11101 +
b11101 5"
b1 ,
b1 4"
b1 0
b1 3"
b1111111 <
b1111111 J
b0 =
b0 I
b10011 5
b10011 K
b11111111111111111111111111111101 ;
b11111111111111111111111111111101 -"
b11111111111111111111111111111101 1"
b11111111110100001000000010010011 :
b11111111110100001000000010010011 %"
b11111111110100001000000010010011 ."
b10100 1
b10000 2
b10000 /"
b10000 2"
b101 ;"
b101 :"
b111100000110001 <"
1!
#46000
b100 ;"
b100 :"
b111100000110010 <"
#47000
b1001 ;"
b1001 :"
b111100000110011 <"
#48000
b11011010110010101101101010110110011000001011101 <"
#50000
0!
#55000
b1001 /
b1001 ""
1'
b1 -
b1 }
18
1A
1.
b0 @
b0 E
b1001 (
b1001 6"
b11 $"
b0 +
b0 5"
b0 ,
b0 4"
b10 0
b10 3"
b0 <
b0 J
b10 =
b10 I
b11 5
b11 K
b0 ;
b0 -"
b0 1"
06
b0 H
0>
b0 %
b0 ~
b0 4
b0 G
b10000100000011 :
b10000100000011 %"
b10000100000011 ."
b0 $
b0 D
b0 *
b0 8"
b11000 1
b10100 2
b10100 /"
b10100 2"
1!
#60000
0!
#65000
1>
b111 (
b111 6"
b0 /
b0 ""
06
b111 %
b111 ~
b111 4
b111 G
b111 H
0'
b10 &
b10 !"
b10 )
b10 7"
b1001 $
b1001 D
b1001 *
b1001 8"
b1 B
b1 F
b1 |
b0 -
b0 }
0A
08
1.
b10 @
b10 E
b110011 $"
b1 +
b1 5"
b10 ,
b10 4"
b11 0
b11 3"
b100000 <
b100000 J
b0 =
b0 I
b110011 5
b110011 K
b0 ;
b0 -"
b0 1"
b1000000000100010000000110110011 :
b1000000000100010000000110110011 %"
b1000000000100010000000110110011 ."
b11100 1
b11000 2
b11000 /"
b11000 2"
1!
#70000
0!
#75000
b100 (
b100 6"
b111 &
b111 !"
b111 )
b111 7"
b100 @
b100 E
b100 H
0>
b100 %
b100 ~
b100 4
b100 G
b100 ;
b100 -"
b100 1"
b0 $
b0 D
b0 *
b0 8"
1A
17
b0 B
b0 F
b0 |
0.
b100011 $"
b11 +
b11 5"
b0 ,
b0 4"
b100 0
b100 3"
b0 <
b0 J
b10 =
b10 I
b100011 5
b100011 K
b1100000010001000100011 :
b1100000010001000100011 %"
b1100000010001000100011 ."
b100000 1
b11100 2
b11100 /"
b11100 2"
1!
#80000
0!
#85000
b1111 (
b1111 6"
b1111 H
b1111 %
b1111 ~
b1111 4
b1111 G
b0 &
b0 !"
b0 )
b0 7"
b1111 @
b1111 E
b1111 ;
b1111 -"
b1111 1"
1.
1A
07
b10011 $"
b1111 +
b1111 5"
b0 =
b0 I
b10011 5
b10011 K
b111100000000001000010011 :
b111100000000001000010011 %"
b111100000000001000010011 ."
b100100 1
b100000 2
b100000 /"
b100000 2"
b10 ;"
b10 :"
b111100000110001 <"
1!
#86000
b1001 ;"
b1001 :"
b111100000110010 <"
#87000
b111 ;"
b111 :"
b111100000110011 <"
#88000
b11011010110010101101101010110110011000101011101 <"
#90000
0!
#95000
b1010 (
b1010 6"
b1010 H
b1010 %
b1010 ~
b1010 4
b1010 G
b1010 @
b1010 E
b1010 +
b1010 5"
b101 0
b101 3"
b1010 ;
b1010 -"
b1010 1"
b101000000000001010010011 :
b101000000000001010010011 %"
b101000000000001010010011 ."
b101000 1
b100100 2
b100100 /"
b100100 2"
1!
#100000
0!
#105000
0'
b1010 (
b1010 6"
b1010 &
b1010 !"
b1010 )
b1010 7"
b0 H
b1010 %
b1010 ~
b1010 4
b1010 G
b1111 $
b1111 D
b1111 *
b1111 8"
b10 B
b10 F
b10 |
0A
1.
b1010 @
b1010 E
b110011 $"
b101 +
b101 5"
b100 ,
b100 4"
b110 0
b110 3"
b111 =
b111 I
b110011 5
b110011 K
b0 ;
b0 -"
b0 1"
b10100100111001100110011 :
b10100100111001100110011 %"
b10100100111001100110011 ."
b101100 1
b101000 2
b101000 /"
b101000 2"
1!
#110000
0!
#115000
b1111 (
b1111 6"
b1111 %
b1111 ~
b1111 4
b1111 G
b11 B
b11 F
b11 |
1.
b111 0
b111 3"
b110 =
b110 I
b10100100110001110110011 :
b10100100110001110110011 %"
b10100100110001110110011 ."
b110000 1
b101100 2
b101100 /"
b101100 2"
1!
#120000
0!
#125000
b101 (
b101 6"
b101 %
b101 ~
b101 4
b101 G
b100 B
b100 F
b100 |
1.
b1000 0
b1000 3"
b100 =
b100 I
b10100100100010000110011 :
b10100100100010000110011 %"
b10100100100010000110011 ."
b110100 1
b110000 2
b110000 /"
b110000 2"
1!
#130000
0!
#135000
b1000 (
b1000 6"
b1000 @
b1000 E
b1000 H
b1000 %
b1000 ~
b1000 4
b1000 G
b1000 ;
b1000 -"
b1000 1"
b0 $
b0 D
b0 *
b0 8"
1A
17
b0 B
b0 F
b0 |
0.
b100011 $"
b110 +
b110 5"
b0 ,
b0 4"
b10 =
b10 I
b100011 5
b100011 K
b11000000010010000100011 :
b11000000010010000100011 %"
b11000000010010000100011 ."
b111000 1
b110100 2
b110100 /"
b110100 2"
1!
#140000
0!
