rtl/data_mem.v
module data_mem(
    input clk,
    input mem_write,
    input [31:0] addr,
    input [31:0] write_data,
    output [31:0] read_data
);
    reg [31:0] mem [0:511];

    assign read_data = mem[addr[10:2]];

    always @(posedge clk) begin
        if (mem_write) begin
            mem[addr[10:2]] <= write_data;
        end
    end
endmodule

tb/tb_data_mem.v
`timescale 1ns / 1ps

module tb_data_mem;

    reg clk;
    reg mem_write;
    reg [31:0] addr;
    reg [31:0] write_data;
    wire [31:0] read_data;

    integer errors;

    data_mem dut(
        .clk(clk),
        .mem_write(mem_write),
        .addr(addr),
        .write_data(write_data),
        .read_data(read_data)
    );

    always begin
        #5 clk = ~clk;
    end

    task check;
        input [255:0] test_name;
        input [31:0] exp_read;
        begin
            #1;
            if (read_data !== exp_read) begin
                $display("FAIL: test=%s expected = %h, got = %h",
                         test_name, exp_read, read_data);
                errors = errors + 1;
            end else begin
                $display("PASS: test=%s got = %h",
                         test_name, read_data);
            end
        end
    endtask

    initial begin
        $dumpfile("waves/data_mem.vcd");
        $dumpvars(0, tb_data_mem);

        errors = 0;
        // Initial values
        clk = 0;
        mem_write = 1'b0;
        addr = 32'd8;
        write_data = 32'd2;

        $display("Starting data_mem test...");

        // Test 1: writing 2 to mem[2]
        mem_write = 1'b1;
        addr = 32'd8; // mem[2]
        write_data = 32'd2;

        @(posedge clk);
        check("mem[2] = 2", 32'd2);

        // Test 2: writing 3 to mem[2], mem_write = 1'b0 (read only)
        mem_write = 1'b0;
        addr = 32'd8; // mem[2]
        write_data = 32'd3;

        @(posedge clk);
        check("read mem[2]", 32'd2);

        // Test 3: writing a bigger data pattern to a different address, mem[3]
        mem_write = 1'b1;
        addr = 32'd12; // mem[3]
        write_data = 32'ha5a5_5a5a;

        @(posedge clk);
        check("mem[3] = a5a5_5a5a", 32'ha5a5_5a5a);

        // Test 4: original mem[2] is still unchanged
        mem_write = 1'b0;
        addr = 32'd8; // mem[2]
        write_data = 32'hffff_ffff;

        @(posedge clk);
        check("mem[2] const after mem[3] write", 32'd2);

        // Test 5: overwrite existing mem[2] when mem_write = 1
        mem_write = 1'b1;
        addr = 32'd8; // mem[2]
        write_data = 32'h1234_5678;

        @(posedge clk);
        check("overwrite mem[2]", 32'h1234_5678);

        // Test 6: read_data changes immediately when addr changes
        mem_write = 1'b0;
        addr = 32'd12; // mem[3]
        check("read changes to mem[3]", 32'ha5a5_5a5a);

        addr = 32'd8; // mem[2]
        check("read changes back to mem[2]", 32'h1234_5678);

        // Test 7: address aliasing within one 32-bit word
        addr = 32'd9; // still mem[2]
        check("addr 9 aliases mem[2]", 32'h1234_5678);

        addr = 32'd10; // still mem[2]
        check("addr 10 aliases mem[2]", 32'h1234_5678);

        addr = 32'd11; // still mem[2]
        check("addr 11 aliases mem[2]", 32'h1234_5678);

        // Test 8: memory does not change between clock edges
        mem_write = 1'b1;
        addr = 32'd8; // mem[2]
        write_data = 32'hdead_beef;
        #2;
        check("no write before clock edge", 32'h1234_5678);

        @(posedge clk);
        check("write happens at clock edge", 32'hdead_beef);
        
        // FINAL
        if (errors == 0) begin
            $display("ALL DATA_MEM TESTS PASSED");
        end else begin
            $display("DATA_MEM TESTS FAILED: %d errors", errors);
        end

        $finish;

    end

endmodule

waves/data_mem.vcd
$date
	Sun Jul  5 12:13:15 2026
$end
$version
	Icarus Verilog
$end
$timescale
	1ps
$end
$scope module tb_data_mem $end
$var wire 32 ! read_data [31:0] $end
$var reg 32 " addr [31:0] $end
$var reg 1 # clk $end
$var reg 1 $ mem_write $end
$var reg 32 % write_data [31:0] $end
$var integer 32 & errors [31:0] $end
$scope module dut $end
$var wire 32 ' addr [31:0] $end
$var wire 1 # clk $end
$var wire 1 $ mem_write $end
$var wire 32 ( read_data [31:0] $end
$var wire 32 ) write_data [31:0] $end
$upscope $end
$scope task check $end
$var reg 32 * exp_read [31:0] $end
$var reg 256 + test_name [255:0] $end
$upscope $end
$upscope $end
$enddefinitions $end
$comment Show the parameter values. $end
$dumpall
$end
#0
$dumpvars
bx +
bx *
b10 )
bx (
b1000 '
b0 &
b10 %
1$
0#
b1000 "
bx !
$end
#5000
b10 !
b10 (
b10 *
b1101101011001010110110101011011001100100101110100100000001111010010000000110010 +
1#
#6000
b11 %
b11 )
0$
#10000
0#
#15000
b111001001100101011000010110010000100000011011010110010101101101010110110011001001011101 +
1#
#16000
bx !
bx (
b10100101101001010101101001011010 %
b10100101101001010101101001011010 )
b1100 "
b1100 '
1$
#20000
0#
#25000
b10100101101001010101101001011010 !
b10100101101001010101101001011010 (
b10100101101001010101101001011010 *
b11011010110010101101101010110110011001101011101001000000011110100100000011000010011010101100001001101010101111100110101011000010011010101100001 +
1#
#26000
b10 !
b10 (
b11111111111111111111111111111111 %
b11111111111111111111111111111111 )
b1000 "
b1000 '
0$
#30000
0#
#35000
b10 *
b1101101011001010110110101011011001100100101110100100000011000110110111101101110011100110111010000100000011000010110011001110100011001010111001000100000011011010110010101101101010110110011001101011101001000000111011101110010011010010111010001100101 +
1#
#36000
b10010001101000101011001111000 %
b10010001101000101011001111000 )
1$
#40000
0#
#45000
b10010001101000101011001111000 !
b10010001101000101011001111000 (
b10010001101000101011001111000 *
b1101111011101100110010101110010011101110111001001101001011101000110010100100000011011010110010101101101010110110011001001011101 +
1#
#46000
b10100101101001010101101001011010 !
b10100101101001010101101001011010 (
b10100101101001010101101001011010 *
b1110010011001010110000101100100001000000110001101101000011000010110111001100111011001010111001100100000011101000110111100100000011011010110010101101101010110110011001101011101 +
b1100 "
b1100 '
0$
#47000
b10010001101000101011001111000 !
b10010001101000101011001111000 (
b10010001101000101011001111000 *
b11100100110010101100001011001000010000001100011011010000110000101101110011001110110010101110011001000000110001001100001011000110110101100100000011101000110111100100000011011010110010101101101010110110011001001011101 +
b1000 "
b1000 '
#48000
b11000010110010001100100011100100010000000111001001000000110000101101100011010010110000101110011011001010111001100100000011011010110010101101101010110110011001001011101 +
b1001 "
b1001 '
#49000
b1100001011001000110010001110010001000000011000100110000001000000110000101101100011010010110000101110011011001010111001100100000011011010110010101101101010110110011001001011101 +
b1010 "
b1010 '
#50000
b1100001011001000110010001110010001000000011000100110001001000000110000101101100011010010110000101110011011001010111001100100000011011010110010101101101010110110011001001011101 +
b1011 "
b1011 '
0#
#51000
b11011110101011011011111011101111 %
b11011110101011011011111011101111 )
b1000 "
b1000 '
1$
#53000
b110111001101111001000000111011101110010011010010111010001100101001000000110001001100101011001100110111101110010011001010010000001100011011011000110111101100011011010110010000001100101011001000110011101100101 +
#55000
b11011110101011011011111011101111 !
b11011110101011011011111011101111 (
b11011110101011011011111011101111 *
b11101110111001001101001011101000110010100100000011010000110000101110000011100000110010101101110011100110010000001100001011101000010000001100011011011000110111101100011011010110010000001100101011001000110011101100101 +
1#
