rtl/imm_gen.v
module imm_gen(
    input [31:0] instr,
    output reg [31:0] imm
);
    // https://msyksphinz-self.github.io/riscv-isadoc/
    wire [6:0] opcode;
    assign opcode = instr[6:0];

    // opcode
    localparam LUI      = 7'b0110111; // lui
    localparam OP_IMM   = 7'b0010011; // addi, slti, xori, ... 
    localparam LOAD     = 7'b0000011; // lb, lbu, lh, lhu, lw
    localparam STORE    = 7'b0100011; // sb, sh, sw
    localparam BRANCH   = 7'b1100011; // beq, bne, blt, bge, bltu, bgeu
    localparam JAL      = 7'b1101111; // jal
    localparam JALR     = 7'b1100111; // jalr

    always @(*) begin
        case(opcode)
            LUI: begin
                imm = {instr[31:12], 12'b0};
            end
            OP_IMM, LOAD: begin
                imm = {{20{instr[31]}}, instr[31:20]};
            end
            STORE: begin
                imm = {{20{instr[31]}}, instr[31:25], instr[11:7]};
            end
            BRANCH: begin
                imm = {{19{instr[31]}}, instr[31], instr[7], instr[30:25], instr[11:8], 1'b0};
            end
            JAL: begin
                imm = {{11{instr[31]}}, instr[31], instr[19:12], instr[20], instr[30:21], 1'b0};
            end
            JALR: begin
                imm = {{20{instr[31]}}, instr[31:20]};
            end
            default: imm = 32'd0;
        endcase
    end

endmodule

tb/tb_imm_gen.v
`timescale 1ns / 1ps

module tb_imm_gen;
    reg  [31:0] instr;
    wire [31:0] imm;

    localparam LUI    = 7'b0110111;
    localparam OP_IMM = 7'b0010011;
    localparam LOAD   = 7'b0000011;
    localparam STORE  = 7'b0100011;
    localparam BRANCH = 7'b1100011;
    localparam JAL    = 7'b1101111;
    localparam JALR   = 7'b1100111;

    integer errors;

    imm_gen dut (
        .instr(instr),
        .imm(imm)
    );

    task check;
        input [255:0] test_name;
        input [31:0] expected;
        begin
            #1;
            if (imm !== expected) begin
                $display("FAIL: test=%s instr=%h expected=%h got=%h",
                         test_name, instr, expected, imm);
                errors = errors + 1;
            end else begin
                $display("PASS: test=%s instr=%h imm=%h",
                         test_name, instr, imm);
            end
        end
    endtask

    initial begin
        $dumpfile("waves/imm_gen.vcd");
        $dumpvars(0, tb_imm_gen);

        errors = 0;

        $display("Starting imm_gen test...");

        // OP_IMM / I-type: addi x2, x1, 51
        instr = {12'h033, 5'd1, 3'b000, 5'd2, OP_IMM};
        check("OP_IMM positive imm=51", 32'd51);

        // OP_IMM / I-type: addi x2, x1, -1
        instr = {12'hfff, 5'd1, 3'b000, 5'd2, OP_IMM};
        check("OP_IMM negative imm=-1", 32'hffff_ffff);

        // LOAD / I-type: lw x3, 16(x4)
        instr = {12'h010, 5'd4, 3'b010, 5'd3, LOAD};
        check("LOAD positive imm=16", 32'd16);

        // LOAD / I-type: lw x3, -8(x4)
        instr = {12'hff8, 5'd4, 3'b010, 5'd3, LOAD};
        check("LOAD negative imm=-8", 32'hffff_fff8);

        // JALR / I-type: jalr x1, -4(x5)
        instr = {12'hffc, 5'd5, 3'b000, 5'd1, JALR};
        check("JALR negative imm=-4", 32'hffff_fffc);

        // STORE / S-type: sw x6, 20(x7)
        instr = {7'b0000000, 5'd6, 5'd7, 3'b010, 5'b10100, STORE};
        check("STORE positive imm=20", 32'd20);

        // STORE / S-type: sw x6, -16(x7)
        instr = {7'b1111111, 5'd6, 5'd7, 3'b010, 5'b10000, STORE};
        check("STORE negative imm=-16", 32'hffff_fff0);

        // BRANCH / B-type: beq x1, x2, 12
        instr = {1'b0, 6'b000000, 5'd2, 5'd1, 3'b000, 4'b0110, 1'b0, BRANCH};
        check("BRANCH positive imm=12", 32'd12);

        // BRANCH / B-type: beq x1, x2, -4
        instr = {1'b1, 6'b111111, 5'd2, 5'd1, 3'b000, 4'b1110, 1'b1, BRANCH};
        check("BRANCH negative imm=-4", 32'hffff_fffc);

        // JAL / J-type: jal x1, 2048
        instr = {1'b0, 10'b0000000000, 1'b1, 8'h00, 5'd1, JAL};
        check("JAL positive imm=2048", 32'd2048);

        // JAL / J-type: jal x1, -2048
        instr = {1'b1, 10'b0000000000, 1'b1, 8'hff, 5'd1, JAL};
        check("JAL negative imm=-2048", 32'hffff_f800);

        // LUI / U-type: immediate goes into bits [31:12].
        instr = {20'h12345, 5'd10, LUI};
        check("LUI imm[31:12]=0x12345", 32'h1234_5000);

        // LUI / U-type with bit 31 set.
        instr = {20'hf2345, 5'd10, LUI};
        check("LUI imm[31:12]=0xf2345", 32'hf234_5000);

        // Unsupported opcode
        instr = 32'h0000_0000;
        check("DEFAULT unsupported opcode", 32'd0);

        if (errors == 0) begin
            $display("All imm_gen tests passed.");
        end else begin
            $display("imm_gen tests failed with %0d error(s).", errors);
        end

        $finish;
    end
endmodule

waves/imm_gen.vcd
$date
	Fri Jul 10 14:00:01 2026
$end
$version
	Icarus Verilog
$end
$timescale
	1ps
$end
$scope module tb_imm_gen $end
$var wire 32 ! imm [31:0] $end
$var parameter 7 " BRANCH $end
$var parameter 7 # JAL $end
$var parameter 7 $ JALR $end
$var parameter 7 % LOAD $end
$var parameter 7 & LUI $end
$var parameter 7 ' OP_IMM $end
$var parameter 7 ( STORE $end
$var reg 32 ) instr [31:0] $end
$var integer 32 * errors [31:0] $end
$scope module dut $end
$var wire 32 + instr [31:0] $end
$var wire 7 , opcode [6:0] $end
$var parameter 7 - BRANCH $end
$var parameter 7 . JAL $end
$var parameter 7 / JALR $end
$var parameter 7 0 LOAD $end
$var parameter 7 1 LUI $end
$var parameter 7 2 OP_IMM $end
$var parameter 7 3 STORE $end
$var reg 32 4 imm [31:0] $end
$upscope $end
$scope task check $end
$var reg 32 5 expected [31:0] $end
$var reg 256 6 test_name [255:0] $end
$upscope $end
$upscope $end
$enddefinitions $end
$comment Show the parameter values. $end
$dumpall
b100011 3
b10011 2
b110111 1
b11 0
b1100111 /
b1101111 .
b1100011 -
b100011 (
b10011 '
b110111 &
b11 %
b1100111 $
b1101111 #
b1100011 "
$end
#0
$dumpvars
b1001111010100000101111101001001010011010100110100100000011100000110111101110011011010010111010001101001011101100110010100100000011010010110110101101101001111010011010100110001 6
b110011 5
b110011 4
b10011 ,
b11001100001000000100010011 +
b0 *
b11001100001000000100010011 )
b110011 !
$end
#1000
b11111111111111111111111111111111 !
b11111111111111111111111111111111 4
b11111111111111111111111111111111 5
b1001111010100000101111101001001010011010100110100100000011011100110010101100111011000010111010001101001011101100110010100100000011010010110110101101101001111010010110100110001 6
b11111111111100001000000100010011 )
b11111111111100001000000100010011 +
#2000
b10000 !
b10000 4
b11 ,
b10000 5
b100110001001111010000010100010000100000011100000110111101110011011010010111010001101001011101100110010100100000011010010110110101101101001111010011000100110110 6
b1000000100010000110000011 )
b1000000100010000110000011 +
#3000
b11111111111111111111111111111000 !
b11111111111111111111111111111000 4
b11111111111111111111111111111000 5
b100110001001111010000010100010000100000011011100110010101100111011000010111010001101001011101100110010100100000011010010110110101101101001111010010110100111000 6
b11111111100000100010000110000011 )
b11111111100000100010000110000011 +
#4000
b11111111111111111111111111111100 !
b11111111111111111111111111111100 4
b1100111 ,
b11111111111111111111111111111100 5
b100101001000001010011000101001000100000011011100110010101100111011000010111010001101001011101100110010100100000011010010110110101101101001111010010110100110100 6
b11111111110000101000000011100111 )
b11111111110000101000000011100111 +
#5000
b10100 !
b10100 4
b100011 ,
b10100 5
b10100110101010001001111010100100100010100100000011100000110111101110011011010010111010001101001011101100110010100100000011010010110110101101101001111010011001000110000 6
b11000111010101000100011 )
b11000111010101000100011 +
#6000
b11111111111111111111111111110000 !
b11111111111111111111111111110000 4
b11111111111111111111111111110000 5
b1010011010101000100111101010010010001010010000001101110011001010110011101100001011101000110100101110110011001010010000001101001011011010110110100111101001011010011000100110110 6
b11111110011000111010100000100011 )
b11111110011000111010100000100011 +
#7000
b1100 !
b1100 4
b1100011 ,
b1100 5
b1000010010100100100000101001110010000110100100000100000011100000110111101110011011010010111010001101001011101100110010100100000011010010110110101101101001111010011000100110010 6
b1000001000011001100011 )
b1000001000011001100011 +
#8000
b11111111111111111111111111111100 !
b11111111111111111111111111111100 4
b11111111111111111111111111111100 5
b1000010010100100100000101001110010000110100100000100000011011100110010101100111011000010111010001101001011101100110010100100000011010010110110101101101001111010010110100110100 6
b11111110001000001000111011100011 )
b11111110001000001000111011100011 +
#9000
b100000000000 !
b100000000000 4
b1101111 ,
b100000000000 5
b10010100100000101001100001000000111000001101111011100110110100101110100011010010111011001100101001000000110100101101101011011010011110100110010001100000011010000111000 6
b100000000000011101111 )
b100000000000011101111 +
#10000
b11111111111111111111100000000000 !
b11111111111111111111100000000000 4
b11111111111111111111100000000000 5
b1001010010000010100110000100000011011100110010101100111011000010111010001101001011101100110010100100000011010010110110101101101001111010010110100110010001100000011010000111000 6
b10000000000111111111000011101111 )
b10000000000111111111000011101111 +
#11000
b10010001101000101000000000000 !
b10010001101000101000000000000 4
b110111 ,
b10010001101000101000000000000 5
b1001100010101010100100100100000011010010110110101101101010110110011001100110001001110100011000100110010010111010011110100110000011110000011000100110010001100110011010000110101 6
b10010001101000101010100110111 )
b10010001101000101010100110111 +
#12000
b11110010001101000101000000000000 !
b11110010001101000101000000000000 4
b11110010001101000101000000000000 5
b1001100010101010100100100100000011010010110110101101101010110110011001100110001001110100011000100110010010111010011110100110000011110000110011000110010001100110011010000110101 6
b11110010001101000101010100110111 )
b11110010001101000101010100110111 +
#13000
b0 !
b0 4
b0 ,
b0 5
b100010001000101010001100100000101010101010011000101010000100000011101010110111001110011011101010111000001110000011011110111001001110100011001010110010000100000011011110111000001100011011011110110010001100101 6
b0 )
b0 +
