rtl/instr_mem.v
module instr_mem(
    input [31:0] pc,
    output [31:0] instr
);
    reg [31:0] mem [0:511]; // 2KB instruction space
    
    initial begin
        $readmemh("tb/programs/add_test.hex", mem);
    end

    assign instr = mem[pc[10:2]]; // 9 bits of PC

endmodule

tb/tb_instr_mem.v
`timescale 1ns / 1ps

module tb_instr_mem;
    reg [31:0] pc;
    wire [31:0] instr;

    integer errors;

    instr_mem dut(
        .pc(pc),
        .instr(instr)
    );

    task check;
        input [255:0] test_name;
        input [31:0] exp_instr;
        begin
            #1;
            if (instr !== exp_instr) begin
                $display("FAIL: test=%s expected = %h, got = %h",
                         test_name, exp_instr, instr);
                errors = errors + 1;
            end else begin
                $display("PASS: test=%s got = %h",
                         test_name, instr);
            end
        end
    endtask

    initial begin
        $dumpfile("waves/instr_mem.vcd");
        $dumpvars(0, tb_instr_mem);

        errors = 0;
        pc = 32'd0;

        $display("Starting instr_mem test...");

        // Test 1: pc = 0 reads mem[0]
        pc = 32'd0;
        check("pc 0 reads mem[0]", 32'h0000_0093);

        // Test 2: pc = 4 reads mem[1]
        pc = 32'd4;
        check("pc 4 reads mem[1]", 32'h0010_0113);

        // Test 3: pc = 8 reads mem[2]
        pc = 32'd8;
        check("pc 8 reads mem[2]", 32'h0020_81b3);

        // Test 4: read changes immediately when pc changes
        pc = 32'd12;
        check("pc change reads mem[3]", 32'h0031_8233);

        pc = 32'd8;
        check("pc change back reads mem[2]", 32'h0020_81b3);

        // Test 5: address aliasing inside one 32-bit instruction word
        pc = 32'd9;
        check("pc 9 aliases mem[2]", 32'h0020_81b3);

        pc = 32'd10;
        check("pc 10 aliases mem[2]", 32'h0020_81b3);

        pc = 32'd11;
        check("pc 11 aliases mem[2]", 32'h0020_81b3);

        // Test 6: highest valid address for mem[0:511]
        pc = 32'd2044; // 511 * 4
        check("pc 2044 reads mem[511]", 32'hffff_ffff);

        // FINAL
        if (errors == 0) begin
            $display("ALL INSTR_MEM TESTS PASSED");
        end else begin
            $display("INSTR_MEM TESTS FAILED: %d errors", errors);
        end

        $finish;
    end

endmodule

waves/instr_mem.vcd
$date
	Sun Jul  5 12:36:17 2026
$end
$version
	Icarus Verilog
$end
$timescale
	1ps
$end
$scope module tb_instr_mem $end
$var wire 32 ! instr [31:0] $end
$var reg 32 " pc [31:0] $end
$var integer 32 # errors [31:0] $end
$scope module dut $end
$var wire 32 $ instr [31:0] $end
$var wire 32 % pc [31:0] $end
$upscope $end
$scope task check $end
$var reg 32 & exp_instr [31:0] $end
$var reg 256 ' test_name [255:0] $end
$upscope $end
$upscope $end
$enddefinitions $end
$comment Show the parameter values. $end
$dumpall
$end
#0
$dumpvars
b111000001100011001000000011000000100000011100100110010101100001011001000111001100100000011011010110010101101101010110110011000001011101 '
b10010011 &
b0 %
b10010011 $
b0 #
b0 "
b10010011 !
$end
#1000
b100000000000100010011 !
b100000000000100010011 $
b100000000000100010011 &
b111000001100011001000000011010000100000011100100110010101100001011001000111001100100000011011010110010101101101010110110011000101011101 '
b100 "
b100 %
#2000
b1000001000000110110011 !
b1000001000000110110011 $
b1000001000000110110011 &
b111000001100011001000000011100000100000011100100110010101100001011001000111001100100000011011010110010101101101010110110011001001011101 '
b1000 "
b1000 %
#3000
b1100011000001000110011 !
b1100011000001000110011 $
b1100011000001000110011 &
b1110000011000110010000001100011011010000110000101101110011001110110010100100000011100100110010101100001011001000111001100100000011011010110010101101101010110110011001101011101 '
b1100 "
b1100 %
#4000
b1000001000000110110011 !
b1000001000000110110011 $
b1000001000000110110011 &
b11100000110001100100000011000110110100001100001011011100110011101100101001000000110001001100001011000110110101100100000011100100110010101100001011001000111001100100000011011010110010101101101010110110011001001011101 '
b1000 "
b1000 %
#5000
b1110000011000110010000000111001001000000110000101101100011010010110000101110011011001010111001100100000011011010110010101101101010110110011001001011101 '
b1001 "
b1001 %
#6000
b111000001100011001000000011000100110000001000000110000101101100011010010110000101110011011001010111001100100000011011010110010101101101010110110011001001011101 '
b1010 "
b1010 %
#7000
b111000001100011001000000011000100110001001000000110000101101100011010010110000101110011011001010111001100100000011011010110010101101101010110110011001001011101 '
b1011 "
b1011 %
#8000
b11111111111111111111111111111111 !
b11111111111111111111111111111111 $
b11111111111111111111111111111111 &
b1110000011000110010000000110010001100000011010000110100001000000111001001100101011000010110010001110011001000000110110101100101011011010101101100110101001100010011000101011101 '
b11111111100 "
b11111111100 %
