rtl/pc.v
module pc(
    input clk,
    input reset,
    input branch,
    input jump,
    input [31:0] imm,
    output reg [31:0] pc
);

    always @(posedge clk) begin
        if (reset) begin
            pc <= 32'h0;
        end else if (jump || branch) begin
            pc <= pc + imm;
        end else begin
            pc <= pc + 32'd4;
        end
    end

endmodule

tb/tb_pc.v
`timescale 1ns / 1ps
module tb_pc;

    reg clk;
    reg reset;
    reg branch;
    reg jump;
    reg [31:0] imm;
    wire [31:0] pc;

    integer errors;

    pc dut (
        .clk(clk),
        .reset(reset),
        .branch(branch),
        .jump(jump),
        .imm(imm),
        .pc(pc)
    );

    always begin
        #5 clk = ~clk;
    end

    task check;
        input [255:0] test_name;
        input [31:0] exp_pc;
        begin
            #1;
            if (exp_pc !== pc) begin
                $display("FAIL: test=%s expected=%h got=%h",
                            test_name, exp_pc, pc);
                errors = errors + 1;
            end else begin
                $display("PASS: test=%s got=%h",
                            test_name, pc);
            end
        end
    endtask

    initial begin
        $dumpfile("waves/pc.vcd");
        $dumpvars(0, tb_pc);

        errors = 0;
        clk = 0;

        $display("Starting pc test...");
        
        // Test 0: reset
        reset = 1;
        branch = 0;
        jump = 0;
        imm = 32'd0;
        @(posedge clk);
        check("Reset", 32'd0);

        // Test 1: normal pc behavior
        reset = 0;
        branch = 0;
        jump = 0;
        imm = 32'd0;
        @(posedge clk);
        check("Normal", 32'd4);

        // Test 2: jump by 8
        reset = 0;
        branch = 0;
        jump = 1;
        imm = 32'd8;
        @(posedge clk);
        check("Jump (8)", 32'd12);

        // Test 3: branch by 12
        reset = 0;
        branch = 1;
        jump = 0;
        imm = 32'd12;
        @(posedge clk);
        check("Branch (12)", 32'd24);

        // Test 4: reset (highest priority)
        reset = 1;
        branch = 1;
        jump = 0;
        imm = 32'd4;
        @(posedge clk);
        check("Reset (highest priority)", 32'd0);

        // Test 5: behavior after reset is released
        reset = 0;
        branch = 0;
        jump = 0;
        imm = 32'd0;
        @(posedge clk);
        check("After reset release", 32'd4);

        // Test 6: branch with negative immediate, 4 + (-4) = 0
        reset = 0;
        branch = 1;
        jump = 0;
        imm = 32'hffff_fffc;
        @(posedge clk);
        check("Branch negative imm (-4)", 32'd0);

        // Test 7: jump with zero immediate keeps pc the same
        reset = 0;
        branch = 0;
        jump = 1;
        imm = 32'd0;
        @(posedge clk);
        check("Jump zero imm", 32'd0);

        // Test 8: larger immediate
        reset = 0;
        branch = 0;
        jump = 1;
        imm = 32'd1024;
        @(posedge clk);
        check("Jump larger imm (1024)", 32'd1024);

        // Test 9: pc does not change between clock edges
        reset = 0;
        branch = 0;
        jump = 0;
        imm = 32'd0;
        #2;
        check("Stable between clock edges", 32'd1024);

        @(posedge clk);
        check("Next normal after stable", 32'd1028);

        if (errors == 0) begin
            $display("All pc tests passed.");
        end else begin
            $display("pc tests failed with %0d error(s).", errors);
        end

        $finish;

    end

endmodule

waves/pc.vcd
$date
	Sun Jul  5 12:14:21 2026
$end
$version
	Icarus Verilog
$end
$timescale
	1ps
$end
$scope module tb_pc $end
$var wire 32 ! pc [31:0] $end
$var reg 1 " branch $end
$var reg 1 # clk $end
$var reg 32 $ imm [31:0] $end
$var reg 1 % jump $end
$var reg 1 & reset $end
$var integer 32 ' errors [31:0] $end
$scope module dut $end
$var wire 1 " branch $end
$var wire 1 # clk $end
$var wire 32 ( imm [31:0] $end
$var wire 1 % jump $end
$var wire 1 & reset $end
$var reg 32 ) pc [31:0] $end
$upscope $end
$scope task check $end
$var reg 32 * exp_pc [31:0] $end
$var reg 256 + test_name [255:0] $end
$upscope $end
$upscope $end
$enddefinitions $end
$comment Show the parameter values. $end
$dumpall
$end
#0
$dumpvars
bx +
bx *
bx )
b0 (
b0 '
1&
0%
b0 $
0#
0"
bx !
$end
#5000
b0 !
b0 )
b0 *
b101001001100101011100110110010101110100 +
1#
#6000
0&
#10000
0#
#15000
b100 !
b100 )
b100 *
b10011100110111101110010011011010110000101101100 +
1#
#16000
b1000 $
b1000 (
1%
#20000
0#
#25000
b1100 !
b1100 )
b1100 *
b100101001110101011011010111000000100000001010000011100000101001 +
1#
#26000
b1100 $
b1100 (
0%
1"
#30000
0#
#35000
b11000 !
b11000 )
b11000 *
b100001001110010011000010110111001100011011010000010000000101000001100010011001000101001 +
1#
#36000
b100 $
b100 (
1&
#40000
0#
#45000
b0 !
b0 )
b0 *
b10100100110010101110011011001010111010000100000001010000110100001101001011001110110100001100101011100110111010000100000011100000111001001101001011011110111001001101001011101000111100100101001 +
1#
#46000
b0 $
b0 (
0"
0&
#50000
0#
#55000
b100 !
b100 )
b100 *
b1000001011001100111010001100101011100100010000001110010011001010111001101100101011101000010000001110010011001010110110001100101011000010111001101100101 +
1#
#56000
b11111111111111111111111111111100 $
b11111111111111111111111111111100 (
1"
#60000
0#
#65000
b0 !
b0 )
b0 *
b10000100111001001100001011011100110001101101000001000000110111001100101011001110110000101110100011010010111011001100101001000000110100101101101011011010010000000101000001011010011010000101001 +
1#
#66000
b0 $
b0 (
1%
0"
#70000
0#
#75000
b1001010011101010110110101110000001000000111101001100101011100100110111100100000011010010110110101101101 +
1#
#76000
b10000000000 $
b10000000000 (
#80000
0#
#85000
b10000000000 !
b10000000000 )
b10000000000 *
b1001010011101010110110101110000001000000110110001100001011100100110011101100101011100100010000001101001011011010110110100100000001010000011000100110000001100100011010000101001 +
1#
#86000
b0 $
b0 (
0%
#88000
b101001101110100011000010110001001101100011001010010000001100010011001010111010001110111011001010110010101101110001000000110001101101100011011110110001101101011001000000110010101100100011001110110010101110011 +
#90000
0#
#95000
b10000000100 !
b10000000100 )
b10000000100 *
b10011100110010101111000011101000010000001101110011011110111001001101101011000010110110000100000011000010110011001110100011001010111001000100000011100110111010001100001011000100110110001100101 +
1#
