rtl/regfile.v
module regfile(
    input clk, 
    input w_en,             // regfile allowed to write when w_en = 1
    input  [4:0]rs1,        // 32 registers --> 5 bits
    input  [4:0]rs2, 
    input  [4:0]rd, 
    input  [31:0]w_data,    // write data
    output [31:0]rv1,       // read value (of rs1)
    output [31:0]rv2        // read value (of rs2)
    );

    reg [31:0] regs [0:31]; // 32-bit registers * 32

    assign rv1 = (rs1 == 5'd0) ? 32'd0 : regs[rs1]; // rv1 = 0 if rs1 = x0
    assign rv2 = (rs2 == 5'd0) ? 32'd0 : regs[rs2]; // rv2 = 0 if rs2 = x0

    always @(posedge clk) begin
        if (w_en && rd != 5'd0) begin
            regs[rd] <= w_data;     // write w_data into regs[rd]
        end
    end
    
endmodule

tb/tb_regfile.v
`timescale 1ns / 1ps

module tb_regfile;
    reg clk;
    reg w_en;
    reg [4:0] rs1;
    reg [4:0] rs2;
    reg [4:0] rd;
    reg [31:0] w_data;

    wire [31:0] rv1;
    wire [31:0] rv2;

    integer errors;

    regfile dut(
        .clk(clk),
        .w_en(w_en),
        .rs1(rs1),
        .rs2(rs2),
        .rd(rd),
        .w_data(w_data),
        .rv1(rv1),
        .rv2(rv2)
    );

    // clk period: 10 ns
    always begin
        #5 clk = ~clk;
    end

    task check;
        input [127:0] test_name;
        input [31:0] actual;
        input [31:0] expected;
        begin
            if (actual !== expected) begin
                $display("FAIL: test=%s expected = %h, got = %h",
                         test_name, expected, actual);
                errors = errors + 1;
            end else begin
                $display("PASS: test=%s got = %h",
                         test_name, actual);
            end
        end
    endtask

    initial begin
        $dumpfile("waves/regfile.vcd");
        $dumpvars(0, tb_regfile);

        errors = 0;

        // Initial values
        clk = 0;
        w_en = 0;
        rs1 = 5'd0;
        rs2 = 5'd0;
        rd = 5'd0;
        w_data = 32'd0;

        $display("Starting regfile test...");
        
        // Test 1: read rv from rs = x0
        rs1 = 5'd0;
        rs2 = 5'd0;
        #1;

        check("rv1 = x0", rv1, 32'd0);
        check("rv2 = x0", rv2, 32'd0);

        // Test 2: write 100 to x3, then read x3
        rd = 5'd3;
        w_data = 32'd100;
        w_en = 1'b1;

        @(posedge clk);
        #1; 

        w_en = 1'b0;
        rs1 = 5'd3;
        #1;

        check("write, read x3", rv1, 32'd100);

        // Test 3: Read two reg at the same time, x3 = 100, x5 = 123
        rd = 5'd5;
        w_data = 32'd123;
        w_en = 1'b1;

        @(posedge clk);
        #1;
        
        w_en = 1'b0;
        rs1 = 5'd3;
        rs2 = 5'd5;
        #1;
        check("read x3", rv1, 32'd100);
        check("read x5", rv2, 32'd123);

        // Test 4: Try to write to x0 (should not change)
        rd = 5'd0;
        w_data = 32'd0;
        w_en = 1'b1;

        @(posedge clk);
        #1;

        w_en = 1'b0;
        rs1 = 5'd0;
        #1;
        check("write x0", rv1, 32'd0);

        // Test 5: Write when w_en = 0;
        rd = 5'd3;
        w_data = 32'd3;
        w_en = 1'b0;

        @(posedge clk);
        #1;

        rs1 = 5'd3;
        #1;
        check ("write w_en = 0", rv1, 32'd100);

        // FINAL
        if (errors == 0) begin
            $display("ALL REGFILE TESTS PASSED");
        end else begin
            $display("REGFILE TESTS FAILED: %d errors", errors);
        end

        $finish;

    end

endmodule

waves/regfile.vcd
$date
	Sat Jun 27 13:07:12 2026
$end
$version
	Icarus Verilog
$end
$timescale
	1ps
$end
$scope module tb_regfile $end
$var wire 32 ! rv2 [31:0] $end
$var wire 32 " rv1 [31:0] $end
$var reg 1 # clk $end
$var reg 5 $ rd [4:0] $end
$var reg 5 % rs1 [4:0] $end
$var reg 5 & rs2 [4:0] $end
$var reg 32 ' w_data [31:0] $end
$var reg 1 ( w_en $end
$var integer 32 ) errors [31:0] $end
$scope module dut $end
$var wire 1 # clk $end
$var wire 5 * rd [4:0] $end
$var wire 5 + rs1 [4:0] $end
$var wire 5 , rs2 [4:0] $end
$var wire 32 - w_data [31:0] $end
$var wire 1 ( w_en $end
$var wire 32 . rv2 [31:0] $end
$var wire 32 / rv1 [31:0] $end
$upscope $end
$scope task check $end
$var reg 32 0 actual [31:0] $end
$var reg 32 1 expected [31:0] $end
$var reg 128 2 test_name [127:0] $end
$upscope $end
$upscope $end
$enddefinitions $end
$comment Show the parameter values. $end
$dumpall
$end
#0
$dumpvars
bx 2
bx 1
bx 0
b0 /
b0 .
b0 -
b0 ,
b0 +
b0 *
b0 )
0(
b0 '
b0 &
b0 %
b0 $
0#
b0 "
b0 !
$end
#1000
1(
b1100100 '
b1100100 -
b11 $
b11 *
b0 1
b0 0
b111001001110110001100100010000000111101001000000111100000110000 2
#5000
1#
#6000
b1100100 "
b1100100 /
b11 %
b11 +
0(
#7000
1(
b1111011 '
b1111011 -
b101 $
b101 *
b1100100 1
b1100100 0
b111011101110010011010010111010001100101001011000010000001110010011001010110000101100100001000000111100000110011 2
#10000
0#
#15000
1#
#16000
b1111011 !
b1111011 .
b101 &
b101 ,
0(
#17000
1(
b0 '
b0 -
b0 $
b0 *
b1111011 1
b1111011 0
b1110010011001010110000101100100001000000111100000110101 2
#20000
0#
#25000
1#
#26000
b0 "
b0 /
b0 %
b0 +
0(
#27000
b11 '
b11 -
b11 $
b11 *
b0 1
b0 0
b111011101110010011010010111010001100101001000000111100000110000 2
#30000
0#
#35000
1#
#36000
b1100100 "
b1100100 /
b11 %
b11 +
#37000
b1100100 1
b1100100 0
b111011101110010011010010111010001100101001000000111011101011111011001010110111000100000001111010010000000110000 2
